{
  "result": {
    "name": "Computer Engineering, B.S.",
    "type": "Major",
    "publishDate": "2025-10-06T21:57:04.7505627",
    "receivingInstitution": "{\"id\":26,\"code\":\"SDSU    \",\"isCommunityCollege\":false,\"category\":\"CSU\",\"termType\":\"Semester\",\"names\":[{\"name\":\"San Diego State University\",\"hasDepartments\":true,\"fromYear\":0,\"hideInList\":false}],\"termTypeAcademicYears\":[{\"termType\":\"Semester\",\"fromYear\":1980}],\"beginId\":31,\"endId\":null}",
    "sendingInstitution": "{\"id\":113,\"code\":\"DAC     \",\"isCommunityCollege\":true,\"category\":\"CCC\",\"termType\":\"Quarter\",\"names\":[{\"name\":\"De Anza College\",\"hasDepartments\":true,\"fromYear\":0,\"hideInList\":false}],\"termTypeAcademicYears\":[{\"termType\":\"Quarter\",\"fromYear\":1980}],\"beginId\":31,\"endId\":null}",
    "academicYear": "{\"id\":76,\"code\":\"2025-2026\",\"beginDate\":\"2025-10-01T00:00:00\",\"endDate\":\"2026-10-01T00:00:00\",\"isOpenForMaintenance\":true,\"isOpenForPublic\":true,\"isOpenForReporting\":true,\"isLocked\":false}",
    "templateAssets": [
      {
        "type": "RequirementTitle",
        "content": "PREPARATION FOR THE MAJOR",
        "groupId": "41327945-6887-ef11-8474-000d3a37e3b6",
        "position": 0,
        "area": "Requirements"
      },
      {
        "type": "RequirementGroup",
        "hideSectionLetters": true,
        "sections": [
          {
            "type": "Section",
            "rows": [
              {
                "position": 0,
                "cells": [
                  {
                    "type": "Course",
                    "course": {
                      "courseIdentifierParentId": 171484,
                      "courseTitle": "Calculus I",
                      "courseNumber": "150",
                      "prefix": "MATH",
                      "prefixParentId": 9932,
                      "prefixDescription": "Mathematics",
                      "departmentParentId": 8967,
                      "department": "Mathematics",
                      "begin": "F2005",
                      "end": "",
                      "minUnits": 4.0,
                      "maxUnits": 4.0,
                      "pathways": []
                    },
                    "visibleCrossListedCourses": [],
                    "requisites": [],
                    "courseAttributes": [
                      {
                        "position": 0,
                        "content": "Minimum grade required: C or better"
                      }
                    ],
                    "id": "9d40389b-f6d4-44c9-1113-08ddd3b241bf",
                    "position": 0,
                    "attributes": []
                  }
                ],
                "attributes": []
              },
              {
                "position": 1,
                "cells": [
                  {
                    "type": "Course",
                    "course": {
                      "courseIdentifierParentId": 352007,
                      "courseTitle": "Calculus II",
                      "courseNumber": "151",
                      "prefix": "MATH",
                      "prefixParentId": 9932,
                      "prefixDescription": "Mathematics",
                      "departmentParentId": 8967,
                      "department": "Mathematics",
                      "begin": "F1994",
                      "end": "",
                      "minUnits": 4.0,
                      "maxUnits": 4.0,
                      "pathways": []
                    },
                    "visibleCrossListedCourses": [],
                    "requisites": [],
                    "courseAttributes": [
                      {
                        "position": 0,
                        "content": "Minimum grade required: C or better"
                      }
                    ],
                    "id": "608b28c5-ebc1-446e-1114-08ddd3b241bf",
                    "position": 0,
                    "attributes": []
                  }
                ],
                "attributes": []
              },
              {
                "position": 2,
                "cells": [
                  {
                    "type": "Course",
                    "course": {
                      "courseIdentifierParentId": 330961,
                      "courseTitle": "Discrete Mathematics",
                      "courseNumber": "245",
                      "prefix": "MATH",
                      "prefixParentId": 9932,
                      "prefixDescription": "Mathematics",
                      "departmentParentId": 8967,
                      "department": "Mathematics",
                      "begin": "F1994",
                      "end": "",
                      "minUnits": 3.0,
                      "maxUnits": 3.0,
                      "pathways": []
                    },
                    "visibleCrossListedCourses": [],
                    "requisites": [],
                    "courseAttributes": [
                      {
                        "position": 0,
                        "content": "Minimum grade required: C- or better"
                      }
                    ],
                    "id": "3dabc5db-b0ff-4b92-1115-08ddd3b241bf",
                    "position": 0,
                    "attributes": []
                  }
                ],
                "attributes": []
              },
              {
                "position": 3,
                "cells": [
                  {
                    "type": "Course",
                    "course": {
                      "courseIdentifierParentId": 136819,
                      "courseTitle": "Introduction to Linear Algebra",
                      "courseNumber": "254",
                      "prefix": "MATH",
                      "prefixParentId": 9932,
                      "prefixDescription": "Mathematics",
                      "departmentParentId": 8967,
                      "department": "Mathematics",
                      "begin": "F1994",
                      "end": "",
                      "minUnits": 3.0,
                      "maxUnits": 3.0,
                      "pathways": []
                    },
                    "visibleCrossListedCourses": [],
                    "requisites": [],
                    "courseAttributes": [
                      {
                        "position": 0,
                        "content": "Minimum grade required: C- or better"
                      }
                    ],
                    "id": "2e89b292-ed26-4a95-1116-08ddd3b241bf",
                    "position": 0,
                    "attributes": []
                  }
                ],
                "attributes": []
              }
            ],
            "advisements": [],
            "position": 0,
            "attributes": []
          }
        ],
        "attributes": [],
        "showConjunctionBetweenSections": false,
        "academicYearId": 0,
        "institutionParentId": 0,
        "instruction": {
          "type": "Following",
          "id": "bb31e6cc-9d4c-496f-a14c-08ddd3b241b0",
          "selectionType": "Complete"
        },
        "advisements": [],
        "groupId": "442b7745-6887-ef11-8474-000d3a37e3b6",
        "position": 3,
        "area": "Requirements"
      },
      {
        "type": "RequirementGroup",
        "hideSectionLetters": false,
        "sections": [
          {
            "type": "Section",
            "rows": [
              {
                "position": 0,
                "cells": [
                  {
                    "type": "Course",
                    "course": {
                      "courseIdentifierParentId": 158892,
                      "courseTitle": "Principles of Physics",
                      "courseNumber": "195",
                      "prefix": "PHYS",
                      "prefixParentId": 205,
                      "prefixDescription": "Physics",
                      "departmentParentId": 10763,
                      "department": "Physics",
                      "begin": "F1994",
                      "end": "",
                      "minUnits": 3.0,
                      "maxUnits": 3.0,
                      "pathways": []
                    },
                    "visibleCrossListedCourses": [],
                    "requisites": [],
                    "courseAttributes": [
                      {
                        "position": 0,
                        "content": "Minimum grade required: C or better"
                      }
                    ],
                    "id": "d8c39ffd-df38-49f8-1117-08ddd3b241bf",
                    "position": 0,
                    "attributes": []
                  }
                ],
                "attributes": []
              }
            ],
            "advisements": [],
            "position": 0,
            "attributes": []
          },
          {
            "type": "Section",
            "rows": [
              {
                "position": 0,
                "cells": [
                  {
                    "type": "Series",
                    "series": {
                      "conjunction": "And",
                      "name": "PHYS 195, PHYS 195L",
                      "courses": [
                        {
                          "id": "aa02889c-3963-40c0-dd1d-08ddd3b23ad5",
                          "position": 0,
                          "courseIdentifierParentId": 158892,
                          "courseTitle": "Principles of Physics",
                          "courseNumber": "195",
                          "prefix": "PHYS",
                          "prefixParentId": 205,
                          "prefixDescription": "Physics",
                          "departmentParentId": 10763,
                          "department": "Physics",
                          "begin": "F1994",
                          "end": "",
                          "minUnits": 3.0,
                          "maxUnits": 3.0,
                          "pathways": []
                        },
                        {
                          "id": "8d921adf-d70d-49dd-dd1e-08ddd3b23ad5",
                          "position": 1,
                          "courseIdentifierParentId": 44006,
                          "courseTitle": "Principles of Physics Laboratory",
                          "courseNumber": "195L",
                          "prefix": "PHYS",
                          "prefixParentId": 205,
                          "prefixDescription": "Physics",
                          "departmentParentId": 10763,
                          "department": "Physics",
                          "begin": "F1998",
                          "end": "",
                          "minUnits": 1.0,
                          "maxUnits": 1.0,
                          "pathways": []
                        }
                      ],
                      "seriesPathways": []
                    },
                    "requisites": [],
                    "visibleCrossListedCourses": [],
                    "seriesAttributes": [],
                    "courseAttributes": [
                      {
                        "seriesCourseId": "8d921adf-d70d-49dd-dd1e-08ddd3b23ad5",
                        "position": 0,
                        "content": "Minimum grade required: C or better"
                      }
                    ],
                    "id": "616e8330-e1a9-4cab-1118-08ddd3b241bf",
                    "position": 0,
                    "attributes": []
                  }
                ],
                "attributes": []
              }
            ],
            "advisements": [],
            "position": 1,
            "attributes": []
          }
        ],
        "attributes": [],
        "showConjunctionBetweenSections": false,
        "academicYearId": 0,
        "institutionParentId": 0,
        "instruction": {
          "type": "Conjunction",
          "conjunction": "Or",
          "id": "e7361c89-8022-4264-a14d-08ddd3b241b0",
          "selectionType": "Complete"
        },
        "advisements": [],
        "groupId": "d4e17645-6887-ef11-8474-000d3a37e3b6",
        "position": 4,
        "area": "Requirements"
      },
      {
        "type": "GeneralText",
        "content": "<p>Due to high demand, admission to SDSU is highly competitive. General admission information is available at:<a href=\"http://arweb.sdsu.edu/es/admissions/transfers/index.html\" rel=\"noopener noreferrer\" target=\"_blank\">http://arweb.sdsu.edu/es/admissions/transfers/index.html</a>.</p>",
        "groupId": "59e86545-6887-ef11-8474-000d3a37e3b6",
        "position": 0,
        "area": "General"
      },
      {
        "type": "RequirementGroup",
        "hideSectionLetters": true,
        "sections": [
          {
            "type": "Section",
            "rows": [
              {
                "position": 3,
                "cells": [
                  {
                    "type": "Course",
                    "course": {
                      "courseIdentifierParentId": 222675,
                      "courseTitle": "Computer Organization",
                      "courseNumber": "271",
                      "prefix": "COMPE",
                      "prefixParentId": 2883,
                      "prefixDescription": "Computer Engineering",
                      "departmentParentId": 3043,
                      "department": "Computer Engineering",
                      "begin": "F1999",
                      "end": "",
                      "minUnits": 3.0,
                      "maxUnits": 3.0,
                      "pathways": []
                    },
                    "visibleCrossListedCourses": [],
                    "requisites": [],
                    "courseAttributes": [
                      {
                        "position": 0,
                        "content": "Minimum grade required: C- or better"
                      }
                    ],
                    "id": "e87c7bfc-01f4-4e10-1119-08ddd3b241bf",
                    "position": 0,
                    "attributes": []
                  }
                ],
                "attributes": []
              },
              {
                "position": 0,
                "cells": [
                  {
                    "type": "Course",
                    "course": {
                      "courseIdentifierParentId": 136601,
                      "courseTitle": "Introduction to Computer Programming",
                      "courseNumber": "160",
                      "prefix": "COMPE",
                      "prefixParentId": 2883,
                      "prefixDescription": "Computer Engineering",
                      "departmentParentId": 3043,
                      "department": "Computer Engineering",
                      "begin": "F2001",
                      "end": "",
                      "minUnits": 3.0,
                      "maxUnits": 3.0,
                      "pathways": []
                    },
                    "visibleCrossListedCourses": [],
                    "requisites": [],
                    "courseAttributes": [
                      {
                        "position": 0,
                        "content": "Minimum grade required: C or better"
                      }
                    ],
                    "id": "fb1325d5-1fda-4cac-111a-08ddd3b241bf",
                    "position": 0,
                    "attributes": []
                  }
                ],
                "attributes": []
              },
              {
                "position": 1,
                "cells": [
                  {
                    "type": "Course",
                    "course": {
                      "courseIdentifierParentId": 342873,
                      "courseTitle": "Data Structures and Object-Oriented Programming",
                      "courseNumber": "260",
                      "prefix": "COMPE",
                      "prefixParentId": 2883,
                      "prefixDescription": "Computer Engineering",
                      "departmentParentId": 3043,
                      "department": "Computer Engineering",
                      "begin": "F1999",
                      "end": "",
                      "minUnits": 3.0,
                      "maxUnits": 3.0,
                      "pathways": []
                    },
                    "visibleCrossListedCourses": [],
                    "requisites": [],
                    "courseAttributes": [
                      {
                        "position": 0,
                        "content": "Minimum grade required: C- or better"
                      }
                    ],
                    "id": "1b7bdf56-de54-4eb8-111b-08ddd3b241bf",
                    "position": 0,
                    "attributes": []
                  }
                ],
                "attributes": []
              },
              {
                "position": 2,
                "cells": [
                  {
                    "type": "Course",
                    "course": {
                      "courseIdentifierParentId": 230382,
                      "courseTitle": "Digital Systems",
                      "courseNumber": "270",
                      "prefix": "COMPE",
                      "prefixParentId": 2883,
                      "prefixDescription": "Computer Engineering",
                      "departmentParentId": 3043,
                      "department": "Computer Engineering",
                      "begin": "F1999",
                      "end": "",
                      "minUnits": 3.0,
                      "maxUnits": 3.0,
                      "pathways": []
                    },
                    "visibleCrossListedCourses": [],
                    "requisites": [],
                    "courseAttributes": [
                      {
                        "position": 0,
                        "content": "Minimum grade required: C- or better"
                      }
                    ],
                    "id": "e78afd1a-8816-4c8c-111c-08ddd3b241bf",
                    "position": 0,
                    "attributes": []
                  }
                ],
                "attributes": []
              },
              {
                "position": 4,
                "cells": [
                  {
                    "type": "Course",
                    "course": {
                      "courseIdentifierParentId": 387597,
                      "courseTitle": "Analytical Methods for Electrical Engineers",
                      "courseNumber": "200",
                      "prefix": "E E",
                      "prefixParentId": 5967,
                      "prefixDescription": "Electrical Engineering",
                      "departmentParentId": 4513,
                      "department": "Electrical Engineering",
                      "begin": "F2022",
                      "end": "",
                      "minUnits": 3.0,
                      "maxUnits": 3.0,
                      "pathways": []
                    },
                    "visibleCrossListedCourses": [],
                    "requisites": [],
                    "courseAttributes": [
                      {
                        "position": 0,
                        "content": "Minimum grade required: C- or better"
                      }
                    ],
                    "id": "ce20ffdb-fb2d-416b-111d-08ddd3b241bf",
                    "position": 0,
                    "attributes": []
                  }
                ],
                "attributes": []
              },
              {
                "position": 5,
                "cells": [
                  {
                    "type": "Course",
                    "course": {
                      "courseIdentifierParentId": 136872,
                      "courseTitle": "Circuit Analysis I",
                      "courseNumber": "210",
                      "prefix": "E E",
                      "prefixParentId": 5967,
                      "prefixDescription": "Electrical Engineering",
                      "departmentParentId": 4513,
                      "department": "Electrical Engineering",
                      "begin": "F2001",
                      "end": "",
                      "minUnits": 3.0,
                      "maxUnits": 3.0,
                      "pathways": []
                    },
                    "visibleCrossListedCourses": [],
                    "requisites": [],
                    "courseAttributes": [
                      {
                        "position": 0,
                        "content": "Minimum grade required: C- or better"
                      }
                    ],
                    "id": "df038cc9-0113-482c-111e-08ddd3b241bf",
                    "position": 0,
                    "attributes": []
                  }
                ],
                "attributes": []
              }
            ],
            "advisements": [],
            "position": 0,
            "attributes": []
          }
        ],
        "attributes": [],
        "showConjunctionBetweenSections": false,
        "academicYearId": 0,
        "institutionParentId": 0,
        "instruction": {
          "type": "Following",
          "id": "7ec7b19f-dbbb-4e20-a14e-08ddd3b241b0",
          "selectionType": "Complete"
        },
        "advisements": [],
        "groupId": "54237745-6887-ef11-8474-000d3a37e3b6",
        "position": 1,
        "area": "Requirements"
      },
      {
        "type": "GeneralTitle",
        "content": "Degree Notes",
        "groupId": "0426e436-c364-47d7-84af-0196da229474",
        "position": 1,
        "area": "General"
      },
      {
        "type": "GeneralText",
        "content": "<ol><li>Complete with a grade of C (2.0) or better:&nbsp;<a href=\"https://catalog.sdsu.edu/preview_program.php?catoid=11&amp;poid=10724&amp;returnto=993#tt6218\" rel=\"noopener noreferrer\" target=\"_blank\">E E 210</a>;&nbsp;<a href=\"https://catalog.sdsu.edu/preview_program.php?catoid=11&amp;poid=10724&amp;returnto=993#tt2800\" rel=\"noopener noreferrer\" target=\"_blank\">COMPE 160</a>;&nbsp;<a href=\"https://catalog.sdsu.edu/preview_program.php?catoid=11&amp;poid=10724&amp;returnto=993#tt2984\" rel=\"noopener noreferrer\" target=\"_blank\">MATH 150</a>,&nbsp;<a href=\"https://catalog.sdsu.edu/preview_program.php?catoid=11&amp;poid=10724&amp;returnto=993#tt2693\" rel=\"noopener noreferrer\" target=\"_blank\">MATH 151</a>;&nbsp;<a href=\"https://catalog.sdsu.edu/preview_program.php?catoid=11&amp;poid=10724&amp;returnto=993#tt410\" rel=\"noopener noreferrer\" target=\"_blank\">PHYS 195</a>,&nbsp;<a href=\"https://catalog.sdsu.edu/preview_program.php?catoid=11&amp;poid=10724&amp;returnto=993#tt4006\" rel=\"noopener noreferrer\" target=\"_blank\">PHYS 196</a>. These courses cannot be taken for credit/no credit (Cr/NC). A minimum cumulative GPA of 2.7 is required.</li></ol><p><br></p><p><br></p>",
        "groupId": "546ea469-26d6-4cde-9188-0196da229476",
        "position": 2,
        "area": "General"
      },
      {
        "type": "RequirementGroup",
        "hideSectionLetters": true,
        "sections": [
          {
            "type": "Section",
            "rows": [
              {
                "position": 0,
                "cells": [
                  {
                    "type": "Course",
                    "course": {
                      "courseIdentifierParentId": 158893,
                      "courseTitle": "General Biology",
                      "courseNumber": "100",
                      "prefix": "BIOL",
                      "prefixParentId": 4847,
                      "prefixDescription": "Biology",
                      "departmentParentId": 1698,
                      "department": "Biology",
                      "begin": "F1994",
                      "end": "",
                      "minUnits": 3.0,
                      "maxUnits": 3.0,
                      "pathways": []
                    },
                    "visibleCrossListedCourses": [],
                    "requisites": [],
                    "courseAttributes": [],
                    "id": "dd1d265a-877c-4e0d-111f-08ddd3b241bf",
                    "position": 0,
                    "attributes": []
                  }
                ],
                "attributes": []
              },
              {
                "position": 1,
                "cells": [
                  {
                    "type": "Course",
                    "course": {
                      "courseIdentifierParentId": 330979,
                      "courseTitle": "World of Animals",
                      "courseNumber": "101",
                      "prefix": "BIOL",
                      "prefixParentId": 4847,
                      "prefixDescription": "Biology",
                      "departmentParentId": 1698,
                      "department": "Biology",
                      "begin": "F1994",
                      "end": "",
                      "minUnits": 3.0,
                      "maxUnits": 3.0,
                      "pathways": []
                    },
                    "visibleCrossListedCourses": [],
                    "requisites": [],
                    "courseAttributes": [],
                    "id": "e0354fab-3d4a-4f36-1120-08ddd3b241bf",
                    "position": 0,
                    "attributes": []
                  }
                ],
                "attributes": []
              }
            ],
            "advisements": [],
            "position": 0,
            "attributes": []
          }
        ],
        "attributes": [],
        "showConjunctionBetweenSections": false,
        "academicYearId": 0,
        "institutionParentId": 0,
        "instruction": {
          "type": "NFromArea",
          "amount": 1.0,
          "amountQuantifier": "None",
          "amountUnitType": "Course",
          "toAmountDeterminer": "None",
          "toAmount": null,
          "areaType": "None",
          "id": "06694d02-1ffd-4942-a14f-08ddd3b241b0",
          "selectionType": "Complete"
        },
        "advisements": [],
        "groupId": "1912488a-438e-4cbd-9df7-0196da229477",
        "position": 2,
        "area": "Requirements"
      },
      {
        "type": "RequirementGroup",
        "hideSectionLetters": false,
        "sections": [
          {
            "type": "Section",
            "rows": [
              {
                "position": 0,
                "cells": [
                  {
                    "type": "Series",
                    "series": {
                      "conjunction": "And",
                      "name": "PHYS 196, PHYS 196L",
                      "courses": [
                        {
                          "id": "68b825cc-57ff-4b65-dd19-08ddd3b23ad5",
                          "position": 0,
                          "courseIdentifierParentId": 331022,
                          "courseTitle": "Principles of Physics",
                          "courseNumber": "196",
                          "prefix": "PHYS",
                          "prefixParentId": 205,
                          "prefixDescription": "Physics",
                          "departmentParentId": 10763,
                          "department": "Physics",
                          "begin": "F1994",
                          "end": "",
                          "minUnits": 3.0,
                          "maxUnits": 3.0,
                          "pathways": []
                        },
                        {
                          "id": "056c2f3b-1c9c-4b59-dd1a-08ddd3b23ad5",
                          "position": 1,
                          "courseIdentifierParentId": 44065,
                          "courseTitle": "Principles of Physics Laboratory",
                          "courseNumber": "196L",
                          "prefix": "PHYS",
                          "prefixParentId": 205,
                          "prefixDescription": "Physics",
                          "departmentParentId": 10763,
                          "department": "Physics",
                          "begin": "F1998",
                          "end": "",
                          "minUnits": 1.0,
                          "maxUnits": 1.0,
                          "pathways": []
                        }
                      ],
                      "seriesPathways": []
                    },
                    "requisites": [],
                    "visibleCrossListedCourses": [],
                    "seriesAttributes": [],
                    "courseAttributes": [
                      {
                        "seriesCourseId": "056c2f3b-1c9c-4b59-dd1a-08ddd3b23ad5",
                        "position": 0,
                        "content": "Minimum grade required: C or better"
                      }
                    ],
                    "id": "935e5345-5830-4f29-1121-08ddd3b241bf",
                    "position": 0,
                    "attributes": []
                  }
                ],
                "attributes": []
              }
            ],
            "advisements": [],
            "position": 0,
            "attributes": []
          },
          {
            "type": "Section",
            "rows": [
              {
                "position": 0,
                "cells": [
                  {
                    "type": "Course",
                    "course": {
                      "courseIdentifierParentId": 331022,
                      "courseTitle": "Principles of Physics",
                      "courseNumber": "196",
                      "prefix": "PHYS",
                      "prefixParentId": 205,
                      "prefixDescription": "Physics",
                      "departmentParentId": 10763,
                      "department": "Physics",
                      "begin": "F1994",
                      "end": "",
                      "minUnits": 3.0,
                      "maxUnits": 3.0,
                      "pathways": []
                    },
                    "visibleCrossListedCourses": [],
                    "requisites": [],
                    "courseAttributes": [
                      {
                        "position": 0,
                        "content": "Minimum grade required: C or better"
                      }
                    ],
                    "id": "aa4a494d-2fe8-4e9f-1122-08ddd3b241bf",
                    "position": 0,
                    "attributes": []
                  }
                ],
                "attributes": []
              },
              {
                "position": 1,
                "cells": [
                  {
                    "type": "Course",
                    "course": {
                      "courseIdentifierParentId": 44065,
                      "courseTitle": "Principles of Physics Laboratory",
                      "courseNumber": "196L",
                      "prefix": "PHYS",
                      "prefixParentId": 205,
                      "prefixDescription": "Physics",
                      "departmentParentId": 10763,
                      "department": "Physics",
                      "begin": "F1998",
                      "end": "",
                      "minUnits": 1.0,
                      "maxUnits": 1.0,
                      "pathways": []
                    },
                    "visibleCrossListedCourses": [],
                    "requisites": [],
                    "courseAttributes": [
                      {
                        "position": 0,
                        "content": "Minimum grade required: C or better"
                      }
                    ],
                    "id": "d08fb4e7-dfe3-4a1e-1123-08ddd3b241bf",
                    "position": 0,
                    "attributes": []
                  }
                ],
                "attributes": []
              }
            ],
            "advisements": [],
            "position": 1,
            "attributes": []
          }
        ],
        "attributes": [],
        "showConjunctionBetweenSections": false,
        "academicYearId": 0,
        "institutionParentId": 0,
        "instruction": {
          "type": "Conjunction",
          "conjunction": "Or",
          "id": "5794fe62-50ac-46fe-a150-08ddd3b241b0",
          "selectionType": "Complete"
        },
        "advisements": [],
        "groupId": "e2c467cf-458e-4c01-b806-0196da229493",
        "position": 5,
        "area": "Requirements"
      }
    ],
    "articulations": [
      {
        "templateCellId": "9d40389b-f6d4-44c9-1113-08ddd3b241bf",
        "articulation": {
          "type": "Course",
          "course": {
            "courseIdentifierParentId": 171484,
            "courseTitle": "Calculus I",
            "courseNumber": "150",
            "prefix": "MATH",
            "prefixParentId": 9932,
            "prefixDescription": "Mathematics",
            "departmentParentId": 8967,
            "department": "Mathematics",
            "begin": "F2005",
            "end": "",
            "minUnits": 4.0,
            "maxUnits": 4.0,
            "pathways": []
          },
          "visibleCrossListedCourses": [],
          "courseAttributes": [],
          "sendingArticulation": {
            "noArticulationReason": null,
            "deniedCourses": [],
            "items": [
              {
                "courseConjunction": "And",
                "items": [
                  {
                    "visibleCrossListedCourses": [],
                    "requisites": [],
                    "attributes": [],
                    "courseIdentifierParentId": 288769,
                    "courseTitle": "Calculus II - HONORS",
                    "courseNumber": "1BH",
                    "prefix": "MATH",
                    "prefixParentId": 10025,
                    "prefixDescription": "Mathematics",
                    "departmentParentId": 9040,
                    "department": "Mathematics",
                    "begin": "F2024",
                    "end": "",
                    "minUnits": 5.0,
                    "maxUnits": 5.0,
                    "pathways": [],
                    "publishedCourseIdentifierYearTermId": null,
                    "position": 1,
                    "type": "Course"
                  },
                  {
                    "visibleCrossListedCourses": [],
                    "requisites": [],
                    "attributes": [
                      {
                        "position": 0,
                        "content": "Articulates as a sequence only"
                      }
                    ],
                    "courseIdentifierParentId": 288768,
                    "courseTitle": "Calculus I - HONORS",
                    "courseNumber": "1AH",
                    "prefix": "MATH",
                    "prefixParentId": 10025,
                    "prefixDescription": "Mathematics",
                    "departmentParentId": 9040,
                    "department": "Mathematics",
                    "begin": "F2024",
                    "end": "",
                    "minUnits": 5.0,
                    "maxUnits": 5.0,
                    "pathways": [],
                    "publishedCourseIdentifierYearTermId": null,
                    "position": 0,
                    "type": "Course"
                  }
                ],
                "attributes": [],
                "position": 1,
                "type": "CourseGroup"
              },
              {
                "courseConjunction": "And",
                "items": [
                  {
                    "visibleCrossListedCourses": [],
                    "requisites": [],
                    "attributes": [
                      {
                        "position": 0,
                        "content": "Articulates as a sequence only"
                      }
                    ],
                    "courseIdentifierParentId": 281397,
                    "courseTitle": "Calculus I",
                    "courseNumber": "1A",
                    "prefix": "MATH",
                    "prefixParentId": 10025,
                    "prefixDescription": "Mathematics",
                    "departmentParentId": 9040,
                    "department": "Mathematics",
                    "begin": "F2024",
                    "end": "",
                    "minUnits": 5.0,
                    "maxUnits": 5.0,
                    "pathways": [],
                    "publishedCourseIdentifierYearTermId": null,
                    "position": 0,
                    "type": "Course"
                  },
                  {
                    "visibleCrossListedCourses": [],
                    "requisites": [],
                    "attributes": [],
                    "courseIdentifierParentId": 307949,
                    "courseTitle": "Calculus II",
                    "courseNumber": "1B",
                    "prefix": "MATH",
                    "prefixParentId": 10025,
                    "prefixDescription": "Mathematics",
                    "departmentParentId": 9040,
                    "department": "Mathematics",
                    "begin": "F2024",
                    "end": "",
                    "minUnits": 5.0,
                    "maxUnits": 5.0,
                    "pathways": [],
                    "publishedCourseIdentifierYearTermId": null,
                    "position": 1,
                    "type": "Course"
                  }
                ],
                "attributes": [],
                "position": 0,
                "type": "CourseGroup"
              }
            ],
            "courseGroupConjunctions": [
              {
                "id": "3968e46a-324f-4410-1685-08ddd3b26d80",
                "sendingArticulationId": "3037e6ca-d534-4418-b0c8-08ddd3b26c6a",
                "groupConjunction": "Or",
                "sendingCourseGroupBeginPosition": 0,
                "sendingCourseGroupEndPosition": 1
              }
            ],
            "type": "SendingArticulation",
            "attributes": []
          },
          "templateOverrides": [],
          "attributes": [],
          "receivingAttributes": []
        },
        "receivingAttributes": {
          "type": "Course",
          "courseAttributes": [],
          "attributes": []
        }
      },
      {
        "templateCellId": "608b28c5-ebc1-446e-1114-08ddd3b241bf",
        "articulation": {
          "type": "Course",
          "course": {
            "courseIdentifierParentId": 352007,
            "courseTitle": "Calculus II",
            "courseNumber": "151",
            "prefix": "MATH",
            "prefixParentId": 9932,
            "prefixDescription": "Mathematics",
            "departmentParentId": 8967,
            "department": "Mathematics",
            "begin": "F1994",
            "end": "",
            "minUnits": 4.0,
            "maxUnits": 4.0,
            "pathways": []
          },
          "visibleCrossListedCourses": [],
          "courseAttributes": [],
          "sendingArticulation": {
            "noArticulationReason": null,
            "deniedCourses": [],
            "items": [
              {
                "courseConjunction": "And",
                "items": [
                  {
                    "visibleCrossListedCourses": [],
                    "requisites": [],
                    "attributes": [],
                    "courseIdentifierParentId": 359110,
                    "courseTitle": "Calculus III",
                    "courseNumber": "1C",
                    "prefix": "MATH",
                    "prefixParentId": 10025,
                    "prefixDescription": "Mathematics",
                    "departmentParentId": 9040,
                    "department": "Mathematics",
                    "begin": "F2024",
                    "end": "",
                    "minUnits": 5.0,
                    "maxUnits": 5.0,
                    "pathways": [],
                    "publishedCourseIdentifierYearTermId": null,
                    "position": 1,
                    "type": "Course"
                  },
                  {
                    "visibleCrossListedCourses": [],
                    "requisites": [],
                    "attributes": [
                      {
                        "position": 0,
                        "content": "Articulates as a sequence only"
                      }
                    ],
                    "courseIdentifierParentId": 307949,
                    "courseTitle": "Calculus II",
                    "courseNumber": "1B",
                    "prefix": "MATH",
                    "prefixParentId": 10025,
                    "prefixDescription": "Mathematics",
                    "departmentParentId": 9040,
                    "department": "Mathematics",
                    "begin": "F2024",
                    "end": "",
                    "minUnits": 5.0,
                    "maxUnits": 5.0,
                    "pathways": [],
                    "publishedCourseIdentifierYearTermId": null,
                    "position": 0,
                    "type": "Course"
                  }
                ],
                "attributes": [],
                "position": 0,
                "type": "CourseGroup"
              },
              {
                "courseConjunction": "And",
                "items": [
                  {
                    "visibleCrossListedCourses": [],
                    "requisites": [],
                    "attributes": [],
                    "courseIdentifierParentId": 309559,
                    "courseTitle": "Calculus III - HONORS",
                    "courseNumber": "1CH",
                    "prefix": "MATH",
                    "prefixParentId": 10025,
                    "prefixDescription": "Mathematics",
                    "departmentParentId": 9040,
                    "department": "Mathematics",
                    "begin": "F2024",
                    "end": "",
                    "minUnits": 5.0,
                    "maxUnits": 5.0,
                    "pathways": [],
                    "publishedCourseIdentifierYearTermId": null,
                    "position": 1,
                    "type": "Course"
                  },
                  {
                    "visibleCrossListedCourses": [],
                    "requisites": [],
                    "attributes": [
                      {
                        "position": 0,
                        "content": "Articulates as a sequence only"
                      }
                    ],
                    "courseIdentifierParentId": 288769,
                    "courseTitle": "Calculus II - HONORS",
                    "courseNumber": "1BH",
                    "prefix": "MATH",
                    "prefixParentId": 10025,
                    "prefixDescription": "Mathematics",
                    "departmentParentId": 9040,
                    "department": "Mathematics",
                    "begin": "F2024",
                    "end": "",
                    "minUnits": 5.0,
                    "maxUnits": 5.0,
                    "pathways": [],
                    "publishedCourseIdentifierYearTermId": null,
                    "position": 0,
                    "type": "Course"
                  }
                ],
                "attributes": [],
                "position": 1,
                "type": "CourseGroup"
              }
            ],
            "courseGroupConjunctions": [
              {
                "id": "bdc96667-1e3a-44e4-13e9-08ddd3b26d80",
                "sendingArticulationId": "9fa50a29-0bb2-47d5-743c-08ddd3b26c6a",
                "groupConjunction": "Or",
                "sendingCourseGroupBeginPosition": 0,
                "sendingCourseGroupEndPosition": 1
              }
            ],
            "type": "SendingArticulation",
            "attributes": []
          },
          "templateOverrides": [],
          "attributes": [],
          "receivingAttributes": []
        },
        "receivingAttributes": {
          "type": "Course",
          "courseAttributes": [],
          "attributes": []
        }
      },
      {
        "templateCellId": "3dabc5db-b0ff-4b92-1115-08ddd3b241bf",
        "articulation": {
          "type": "Course",
          "course": {
            "courseIdentifierParentId": 330961,
            "courseTitle": "Discrete Mathematics",
            "courseNumber": "245",
            "prefix": "MATH",
            "prefixParentId": 9932,
            "prefixDescription": "Mathematics",
            "departmentParentId": 8967,
            "department": "Mathematics",
            "begin": "F1994",
            "end": "",
            "minUnits": 3.0,
            "maxUnits": 3.0,
            "pathways": []
          },
          "visibleCrossListedCourses": [],
          "courseAttributes": [],
          "sendingArticulation": {
            "noArticulationReason": null,
            "deniedCourses": [],
            "items": [
              {
                "courseConjunction": "And",
                "items": [
                  {
                    "visibleCrossListedCourses": [],
                    "requisites": [],
                    "attributes": [],
                    "courseIdentifierParentId": 359214,
                    "courseTitle": "Discrete Mathematics",
                    "courseNumber": "22",
                    "prefix": "MATH",
                    "prefixParentId": 10025,
                    "prefixDescription": "Mathematics",
                    "departmentParentId": 9040,
                    "department": "Mathematics",
                    "begin": "F1995",
                    "end": "",
                    "minUnits": 5.0,
                    "maxUnits": 5.0,
                    "pathways": [],
                    "publishedCourseIdentifierYearTermId": null,
                    "position": 0,
                    "type": "Course"
                  }
                ],
                "attributes": [],
                "position": 0,
                "type": "CourseGroup"
              }
            ],
            "courseGroupConjunctions": [],
            "type": "SendingArticulation",
            "attributes": []
          },
          "templateOverrides": [],
          "attributes": [],
          "receivingAttributes": []
        },
        "receivingAttributes": {
          "type": "Course",
          "courseAttributes": [],
          "attributes": []
        }
      },
      {
        "templateCellId": "2e89b292-ed26-4a95-1116-08ddd3b241bf",
        "articulation": {
          "type": "Course",
          "course": {
            "courseIdentifierParentId": 136819,
            "courseTitle": "Introduction to Linear Algebra",
            "courseNumber": "254",
            "prefix": "MATH",
            "prefixParentId": 9932,
            "prefixDescription": "Mathematics",
            "departmentParentId": 8967,
            "department": "Mathematics",
            "begin": "F1994",
            "end": "",
            "minUnits": 3.0,
            "maxUnits": 3.0,
            "pathways": []
          },
          "visibleCrossListedCourses": [],
          "courseAttributes": [],
          "sendingArticulation": {
            "noArticulationReason": null,
            "deniedCourses": [],
            "items": [
              {
                "courseConjunction": "And",
                "items": [
                  {
                    "visibleCrossListedCourses": [],
                    "requisites": [],
                    "attributes": [],
                    "courseIdentifierParentId": 363589,
                    "courseTitle": "Linear Algebra - HONORS",
                    "courseNumber": "2BH",
                    "prefix": "MATH",
                    "prefixParentId": 10025,
                    "prefixDescription": "Mathematics",
                    "departmentParentId": 9040,
                    "department": "Mathematics",
                    "begin": "F2018",
                    "end": "",
                    "minUnits": 5.0,
                    "maxUnits": 5.0,
                    "pathways": [],
                    "publishedCourseIdentifierYearTermId": null,
                    "position": 0,
                    "type": "Course"
                  }
                ],
                "attributes": [],
                "position": 1,
                "type": "CourseGroup"
              },
              {
                "courseConjunction": "And",
                "items": [
                  {
                    "visibleCrossListedCourses": [],
                    "requisites": [],
                    "attributes": [],
                    "courseIdentifierParentId": 302590,
                    "courseTitle": "Linear Algebra",
                    "courseNumber": "2B",
                    "prefix": "MATH",
                    "prefixParentId": 10025,
                    "prefixDescription": "Mathematics",
                    "departmentParentId": 9040,
                    "department": "Mathematics",
                    "begin": "F1995",
                    "end": "",
                    "minUnits": 5.0,
                    "maxUnits": 5.0,
                    "pathways": [],
                    "publishedCourseIdentifierYearTermId": null,
                    "position": 0,
                    "type": "Course"
                  }
                ],
                "attributes": [],
                "position": 0,
                "type": "CourseGroup"
              }
            ],
            "courseGroupConjunctions": [
              {
                "id": "1d5cb002-9194-47a0-1457-08ddd3b26d80",
                "sendingArticulationId": "7c3545b9-9997-4b1d-7fa2-08ddd3b26c6a",
                "groupConjunction": "Or",
                "sendingCourseGroupBeginPosition": 0,
                "sendingCourseGroupEndPosition": 1
              }
            ],
            "type": "SendingArticulation",
            "attributes": []
          },
          "templateOverrides": [],
          "attributes": [],
          "receivingAttributes": []
        },
        "receivingAttributes": {
          "type": "Course",
          "courseAttributes": [],
          "attributes": []
        }
      },
      {
        "templateCellId": "d8c39ffd-df38-49f8-1117-08ddd3b241bf",
        "articulation": {
          "type": "Course",
          "course": {
            "courseIdentifierParentId": 158892,
            "courseTitle": "Principles of Physics",
            "courseNumber": "195",
            "prefix": "PHYS",
            "prefixParentId": 205,
            "prefixDescription": "Physics",
            "departmentParentId": 10763,
            "department": "Physics",
            "begin": "F1994",
            "end": "",
            "minUnits": 3.0,
            "maxUnits": 3.0,
            "pathways": []
          },
          "visibleCrossListedCourses": [],
          "courseAttributes": [],
          "sendingArticulation": {
            "noArticulationReason": "No Course Articulated",
            "deniedCourses": [],
            "items": [],
            "courseGroupConjunctions": [],
            "type": "SendingArticulation",
            "attributes": []
          },
          "templateOverrides": [],
          "attributes": [],
          "receivingAttributes": []
        },
        "receivingAttributes": {
          "type": "Course",
          "courseAttributes": [],
          "attributes": []
        }
      },
      {
        "templateCellId": "e87c7bfc-01f4-4e10-1119-08ddd3b241bf",
        "articulation": {
          "type": "Course",
          "course": {
            "courseIdentifierParentId": 222675,
            "courseTitle": "Computer Organization",
            "courseNumber": "271",
            "prefix": "COMPE",
            "prefixParentId": 2883,
            "prefixDescription": "Computer Engineering",
            "departmentParentId": 3043,
            "department": "Computer Engineering",
            "begin": "F1999",
            "end": "",
            "minUnits": 3.0,
            "maxUnits": 3.0,
            "pathways": []
          },
          "visibleCrossListedCourses": [],
          "courseAttributes": [],
          "sendingArticulation": {
            "noArticulationReason": "No Course Articulated",
            "deniedCourses": [],
            "items": [],
            "courseGroupConjunctions": [],
            "type": "SendingArticulation",
            "attributes": []
          },
          "templateOverrides": [],
          "attributes": [],
          "receivingAttributes": []
        },
        "receivingAttributes": {
          "type": "Course",
          "courseAttributes": [],
          "attributes": []
        }
      },
      {
        "templateCellId": "fb1325d5-1fda-4cac-111a-08ddd3b241bf",
        "articulation": {
          "type": "Course",
          "course": {
            "courseIdentifierParentId": 136601,
            "courseTitle": "Introduction to Computer Programming",
            "courseNumber": "160",
            "prefix": "COMPE",
            "prefixParentId": 2883,
            "prefixDescription": "Computer Engineering",
            "departmentParentId": 3043,
            "department": "Computer Engineering",
            "begin": "F2001",
            "end": "",
            "minUnits": 3.0,
            "maxUnits": 3.0,
            "pathways": []
          },
          "visibleCrossListedCourses": [],
          "courseAttributes": [],
          "sendingArticulation": {
            "noArticulationReason": "Course(s) Denied",
            "deniedCourses": [],
            "items": [],
            "courseGroupConjunctions": [],
            "type": "SendingArticulation",
            "attributes": []
          },
          "templateOverrides": [],
          "attributes": [],
          "receivingAttributes": []
        },
        "receivingAttributes": {
          "type": "Course",
          "courseAttributes": [],
          "attributes": []
        }
      },
      {
        "templateCellId": "1b7bdf56-de54-4eb8-111b-08ddd3b241bf",
        "articulation": {
          "type": "Course",
          "course": {
            "courseIdentifierParentId": 342873,
            "courseTitle": "Data Structures and Object-Oriented Programming",
            "courseNumber": "260",
            "prefix": "COMPE",
            "prefixParentId": 2883,
            "prefixDescription": "Computer Engineering",
            "departmentParentId": 3043,
            "department": "Computer Engineering",
            "begin": "F1999",
            "end": "",
            "minUnits": 3.0,
            "maxUnits": 3.0,
            "pathways": []
          },
          "visibleCrossListedCourses": [],
          "courseAttributes": [],
          "sendingArticulation": {
            "noArticulationReason": null,
            "deniedCourses": [],
            "items": [
              {
                "courseConjunction": "And",
                "items": [
                  {
                    "visibleCrossListedCourses": [],
                    "requisites": [],
                    "attributes": [],
                    "courseIdentifierParentId": 306384,
                    "courseTitle": "Data Abstraction and Structures",
                    "courseNumber": "22C",
                    "prefix": "CIS",
                    "prefixParentId": 2242,
                    "prefixDescription": "Computer Information Systems",
                    "departmentParentId": 3124,
                    "department": "Computer Science and Information Systems",
                    "begin": "F2013",
                    "end": "",
                    "minUnits": 4.5,
                    "maxUnits": 4.5,
                    "pathways": [],
                    "publishedCourseIdentifierYearTermId": null,
                    "position": 0,
                    "type": "Course"
                  }
                ],
                "attributes": [],
                "position": 0,
                "type": "CourseGroup"
              },
              {
                "courseConjunction": "And",
                "items": [
                  {
                    "visibleCrossListedCourses": [],
                    "requisites": [],
                    "attributes": [],
                    "courseIdentifierParentId": 300770,
                    "courseTitle": "Data Abstraction and Structures - HONORS",
                    "courseNumber": "22CH",
                    "prefix": "CIS",
                    "prefixParentId": 2242,
                    "prefixDescription": "Computer Information Systems",
                    "departmentParentId": 3124,
                    "department": "Computer Science and Information Systems",
                    "begin": "F2016",
                    "end": "",
                    "minUnits": 4.5,
                    "maxUnits": 4.5,
                    "pathways": [],
                    "publishedCourseIdentifierYearTermId": null,
                    "position": 0,
                    "type": "Course"
                  }
                ],
                "attributes": [],
                "position": 1,
                "type": "CourseGroup"
              }
            ],
            "courseGroupConjunctions": [
              {
                "id": "25a4b247-7bde-48c2-12fd-08ddd3b26d80",
                "sendingArticulationId": "6b25f117-987f-47b6-5fe2-08ddd3b26c6a",
                "groupConjunction": "Or",
                "sendingCourseGroupBeginPosition": 0,
                "sendingCourseGroupEndPosition": 1
              }
            ],
            "type": "SendingArticulation",
            "attributes": []
          },
          "templateOverrides": [],
          "attributes": [],
          "receivingAttributes": []
        },
        "receivingAttributes": {
          "type": "Course",
          "courseAttributes": [],
          "attributes": []
        }
      },
      {
        "templateCellId": "e78afd1a-8816-4c8c-111c-08ddd3b241bf",
        "articulation": {
          "type": "Course",
          "course": {
            "courseIdentifierParentId": 230382,
            "courseTitle": "Digital Systems",
            "courseNumber": "270",
            "prefix": "COMPE",
            "prefixParentId": 2883,
            "prefixDescription": "Computer Engineering",
            "departmentParentId": 3043,
            "department": "Computer Engineering",
            "begin": "F1999",
            "end": "",
            "minUnits": 3.0,
            "maxUnits": 3.0,
            "pathways": []
          },
          "visibleCrossListedCourses": [],
          "courseAttributes": [],
          "sendingArticulation": {
            "noArticulationReason": "No Course Articulated",
            "deniedCourses": [],
            "items": [],
            "courseGroupConjunctions": [],
            "type": "SendingArticulation",
            "attributes": []
          },
          "templateOverrides": [],
          "attributes": [],
          "receivingAttributes": []
        },
        "receivingAttributes": {
          "type": "Course",
          "courseAttributes": [],
          "attributes": []
        }
      },
      {
        "templateCellId": "df038cc9-0113-482c-111e-08ddd3b241bf",
        "articulation": {
          "type": "Course",
          "course": {
            "courseIdentifierParentId": 136872,
            "courseTitle": "Circuit Analysis I",
            "courseNumber": "210",
            "prefix": "E E",
            "prefixParentId": 5967,
            "prefixDescription": "Electrical Engineering",
            "departmentParentId": 4513,
            "department": "Electrical Engineering",
            "begin": "F2001",
            "end": "",
            "minUnits": 3.0,
            "maxUnits": 3.0,
            "pathways": []
          },
          "visibleCrossListedCourses": [],
          "courseAttributes": [],
          "sendingArticulation": {
            "noArticulationReason": null,
            "deniedCourses": [],
            "items": [
              {
                "courseConjunction": "And",
                "items": [
                  {
                    "visibleCrossListedCourses": [],
                    "requisites": [],
                    "attributes": [],
                    "courseIdentifierParentId": 307940,
                    "courseTitle": "Introduction to Circuit Analysis",
                    "courseNumber": "37",
                    "prefix": "ENGR",
                    "prefixParentId": 3570,
                    "prefixDescription": "Engineering",
                    "departmentParentId": 4803,
                    "department": "Engineering",
                    "begin": "F1995",
                    "end": "",
                    "minUnits": 5.0,
                    "maxUnits": 5.0,
                    "pathways": [],
                    "publishedCourseIdentifierYearTermId": null,
                    "position": 0,
                    "type": "Course"
                  }
                ],
                "attributes": [],
                "position": 0,
                "type": "CourseGroup"
              }
            ],
            "courseGroupConjunctions": [],
            "type": "SendingArticulation",
            "attributes": []
          },
          "templateOverrides": [],
          "attributes": [],
          "receivingAttributes": []
        },
        "receivingAttributes": {
          "type": "Course",
          "courseAttributes": [],
          "attributes": []
        }
      },
      {
        "templateCellId": "dd1d265a-877c-4e0d-111f-08ddd3b241bf",
        "articulation": {
          "type": "Course",
          "course": {
            "courseIdentifierParentId": 158893,
            "courseTitle": "General Biology",
            "courseNumber": "100",
            "prefix": "BIOL",
            "prefixParentId": 4847,
            "prefixDescription": "Biology",
            "departmentParentId": 1698,
            "department": "Biology",
            "begin": "F1994",
            "end": "",
            "minUnits": 3.0,
            "maxUnits": 3.0,
            "pathways": []
          },
          "visibleCrossListedCourses": [],
          "courseAttributes": [],
          "sendingArticulation": {
            "noArticulationReason": "No Course Articulated",
            "deniedCourses": [],
            "items": [],
            "courseGroupConjunctions": [],
            "type": "SendingArticulation",
            "attributes": []
          },
          "templateOverrides": [],
          "attributes": [],
          "receivingAttributes": []
        },
        "receivingAttributes": {
          "type": "Course",
          "courseAttributes": [],
          "attributes": []
        }
      },
      {
        "templateCellId": "e0354fab-3d4a-4f36-1120-08ddd3b241bf",
        "articulation": {
          "type": "Course",
          "course": {
            "courseIdentifierParentId": 330979,
            "courseTitle": "World of Animals",
            "courseNumber": "101",
            "prefix": "BIOL",
            "prefixParentId": 4847,
            "prefixDescription": "Biology",
            "departmentParentId": 1698,
            "department": "Biology",
            "begin": "F1994",
            "end": "",
            "minUnits": 3.0,
            "maxUnits": 3.0,
            "pathways": []
          },
          "visibleCrossListedCourses": [],
          "courseAttributes": [],
          "sendingArticulation": {
            "noArticulationReason": "No Course Articulated",
            "deniedCourses": [],
            "items": [],
            "courseGroupConjunctions": [],
            "type": "SendingArticulation",
            "attributes": []
          },
          "templateOverrides": [],
          "attributes": [],
          "receivingAttributes": []
        },
        "receivingAttributes": {
          "type": "Course",
          "courseAttributes": [],
          "attributes": []
        }
      },
      {
        "templateCellId": "aa4a494d-2fe8-4e9f-1122-08ddd3b241bf",
        "articulation": {
          "type": "Course",
          "course": {
            "courseIdentifierParentId": 331022,
            "courseTitle": "Principles of Physics",
            "courseNumber": "196",
            "prefix": "PHYS",
            "prefixParentId": 205,
            "prefixDescription": "Physics",
            "departmentParentId": 10763,
            "department": "Physics",
            "begin": "F1994",
            "end": "",
            "minUnits": 3.0,
            "maxUnits": 3.0,
            "pathways": []
          },
          "visibleCrossListedCourses": [],
          "courseAttributes": [],
          "sendingArticulation": {
            "noArticulationReason": "No Course Articulated",
            "deniedCourses": [],
            "items": [],
            "courseGroupConjunctions": [],
            "type": "SendingArticulation",
            "attributes": []
          },
          "templateOverrides": [],
          "attributes": [],
          "receivingAttributes": []
        },
        "receivingAttributes": {
          "type": "Course",
          "courseAttributes": [],
          "attributes": []
        }
      },
      {
        "templateCellId": "d08fb4e7-dfe3-4a1e-1123-08ddd3b241bf",
        "articulation": {
          "type": "Course",
          "course": {
            "courseIdentifierParentId": 44065,
            "courseTitle": "Principles of Physics Laboratory",
            "courseNumber": "196L",
            "prefix": "PHYS",
            "prefixParentId": 205,
            "prefixDescription": "Physics",
            "departmentParentId": 10763,
            "department": "Physics",
            "begin": "F1998",
            "end": "",
            "minUnits": 1.0,
            "maxUnits": 1.0,
            "pathways": []
          },
          "visibleCrossListedCourses": [],
          "courseAttributes": [],
          "sendingArticulation": {
            "noArticulationReason": "No Course Articulated",
            "deniedCourses": [],
            "items": [],
            "courseGroupConjunctions": [],
            "type": "SendingArticulation",
            "attributes": []
          },
          "templateOverrides": [],
          "attributes": [],
          "receivingAttributes": []
        },
        "receivingAttributes": {
          "type": "Course",
          "courseAttributes": [],
          "attributes": []
        }
      },
      {
        "templateCellId": "616e8330-e1a9-4cab-1118-08ddd3b241bf",
        "articulation": {
          "type": "Series",
          "series": {
            "conjunction": "And",
            "name": "PHYS 195, PHYS 195L",
            "courses": [
              {
                "id": "aa02889c-3963-40c0-dd1d-08ddd3b23ad5",
                "position": 0,
                "courseIdentifierParentId": 158892,
                "courseTitle": "Principles of Physics",
                "courseNumber": "195",
                "prefix": "PHYS",
                "prefixParentId": 205,
                "prefixDescription": "Physics",
                "departmentParentId": 10763,
                "department": "Physics",
                "begin": "F1994",
                "end": "",
                "minUnits": 3.0,
                "maxUnits": 3.0,
                "pathways": []
              },
              {
                "id": "8d921adf-d70d-49dd-dd1e-08ddd3b23ad5",
                "position": 1,
                "courseIdentifierParentId": 44006,
                "courseTitle": "Principles of Physics Laboratory",
                "courseNumber": "195L",
                "prefix": "PHYS",
                "prefixParentId": 205,
                "prefixDescription": "Physics",
                "departmentParentId": 10763,
                "department": "Physics",
                "begin": "F1998",
                "end": "",
                "minUnits": 1.0,
                "maxUnits": 1.0,
                "pathways": []
              }
            ],
            "seriesPathways": []
          },
          "visibleCrossListedCourses": [],
          "seriesAttributes": [],
          "courseAttributes": [],
          "sendingArticulation": {
            "noArticulationReason": null,
            "deniedCourses": [],
            "items": [
              {
                "courseConjunction": "And",
                "items": [
                  {
                    "visibleCrossListedCourses": [],
                    "requisites": [],
                    "attributes": [],
                    "courseIdentifierParentId": 305519,
                    "courseTitle": "Physics for Scientists and Engineers: Mechanics",
                    "courseNumber": "4A",
                    "prefix": "PHYS",
                    "prefixParentId": 300,
                    "prefixDescription": "Physics",
                    "departmentParentId": 10814,
                    "department": "Physics",
                    "begin": "F1998",
                    "end": "",
                    "minUnits": 6.0,
                    "maxUnits": 6.0,
                    "pathways": [],
                    "publishedCourseIdentifierYearTermId": null,
                    "position": 0,
                    "type": "Course"
                  }
                ],
                "attributes": [],
                "position": 0,
                "type": "CourseGroup"
              }
            ],
            "courseGroupConjunctions": [],
            "type": "SendingArticulation",
            "attributes": []
          },
          "templateOverrides": [],
          "attributes": [],
          "receivingAttributes": []
        },
        "receivingAttributes": {
          "type": "Series",
          "seriesAttributes": [],
          "seriesCourseAttributes": [],
          "attributes": []
        }
      },
      {
        "templateCellId": "935e5345-5830-4f29-1121-08ddd3b241bf",
        "articulation": {
          "type": "Series",
          "series": {
            "conjunction": "And",
            "name": "PHYS 196, PHYS 196L",
            "courses": [
              {
                "id": "68b825cc-57ff-4b65-dd19-08ddd3b23ad5",
                "position": 0,
                "courseIdentifierParentId": 331022,
                "courseTitle": "Principles of Physics",
                "courseNumber": "196",
                "prefix": "PHYS",
                "prefixParentId": 205,
                "prefixDescription": "Physics",
                "departmentParentId": 10763,
                "department": "Physics",
                "begin": "F1994",
                "end": "",
                "minUnits": 3.0,
                "maxUnits": 3.0,
                "pathways": []
              },
              {
                "id": "056c2f3b-1c9c-4b59-dd1a-08ddd3b23ad5",
                "position": 1,
                "courseIdentifierParentId": 44065,
                "courseTitle": "Principles of Physics Laboratory",
                "courseNumber": "196L",
                "prefix": "PHYS",
                "prefixParentId": 205,
                "prefixDescription": "Physics",
                "departmentParentId": 10763,
                "department": "Physics",
                "begin": "F1998",
                "end": "",
                "minUnits": 1.0,
                "maxUnits": 1.0,
                "pathways": []
              }
            ],
            "seriesPathways": []
          },
          "visibleCrossListedCourses": [],
          "seriesAttributes": [],
          "courseAttributes": [],
          "sendingArticulation": {
            "noArticulationReason": null,
            "deniedCourses": [],
            "items": [
              {
                "courseConjunction": "And",
                "items": [
                  {
                    "visibleCrossListedCourses": [],
                    "requisites": [],
                    "attributes": [],
                    "courseIdentifierParentId": 276901,
                    "courseTitle": "Physics for Scientists and Engineers: Electricity and Magnetism",
                    "courseNumber": "4B",
                    "prefix": "PHYS",
                    "prefixParentId": 300,
                    "prefixDescription": "Physics",
                    "departmentParentId": 10814,
                    "department": "Physics",
                    "begin": "F1998",
                    "end": "",
                    "minUnits": 6.0,
                    "maxUnits": 6.0,
                    "pathways": [],
                    "publishedCourseIdentifierYearTermId": null,
                    "position": 0,
                    "type": "Course"
                  }
                ],
                "attributes": [],
                "position": 0,
                "type": "CourseGroup"
              }
            ],
            "courseGroupConjunctions": [],
            "type": "SendingArticulation",
            "attributes": []
          },
          "templateOverrides": [],
          "attributes": [],
          "receivingAttributes": []
        },
        "receivingAttributes": {
          "type": "Series",
          "seriesAttributes": [],
          "seriesCourseAttributes": [],
          "attributes": []
        }
      }
    ],
    "catalogYear": "{\"receivingCatalogYearBegin\":2025,\"receivingCatalogYearEnd\":2026,\"sendingCatalogYearBegin\":2025,\"sendingCatalogYearEnd\":2026}"
  },
  "validationFailure": null,
  "isSuccessful": true
}