{
  "result": {
    "name": "Liberal Studies Hutchins, B.A.",
    "type": "Major",
    "publishDate": "2026-01-05T23:10:40.122096",
    "receivingInstitution": "{\"id\":88,\"code\":\"SSU     \",\"isCommunityCollege\":false,\"category\":\"CSU\",\"termType\":\"Semester\",\"names\":[{\"name\":\"Sonoma State University\",\"hasDepartments\":true,\"fromYear\":0,\"hideInList\":false}],\"termTypeAcademicYears\":[{\"termType\":\"Semester\",\"fromYear\":1980}],\"beginId\":31,\"endId\":null}",
    "sendingInstitution": "{\"id\":113,\"code\":\"DAC     \",\"isCommunityCollege\":true,\"category\":\"CCC\",\"termType\":\"Quarter\",\"names\":[{\"name\":\"De Anza College\",\"hasDepartments\":true,\"fromYear\":0,\"hideInList\":false}],\"termTypeAcademicYears\":[{\"termType\":\"Quarter\",\"fromYear\":1980}],\"beginId\":31,\"endId\":null}",
    "academicYear": "{\"id\":76,\"code\":\"2025-2026\",\"beginDate\":\"2025-10-01T00:00:00\",\"endDate\":\"2026-10-01T00:00:00\",\"isOpenForMaintenance\":true,\"isOpenForPublic\":true,\"isOpenForReporting\":true,\"isLocked\":false}",
    "templateAssets": [
      {
        "type": "GeneralText",
        "content": "This agreement is subject to revision without prior notice.  Please check with a counselor every semester to obtain current information about possible changes in the agreement.  To learn more about the courses and programs offered at Sonoma State University or the General Education and Upper-division requirements for each major please refer to the university catalog at: <a href=\"http://www.sonoma.edu/catalog/\" target=\"_blank\">http://www.sonoma.edu/catalog/</a>",
        "groupId": "d2ed7145-6887-ef11-8474-000d3a37e3b6",
        "position": 1,
        "area": "General"
      },
      {
        "type": "GeneralText",
        "content": "<p>The Liberal Studies major requirements are upper division requirements.  It's recommend transfer students apply to the program with their GE and American Institutions requirements completed.</p><p><br></p>",
        "groupId": "95027045-6887-ef11-8474-000d3a37e3b6",
        "position": 3,
        "area": "General"
      },
      {
        "type": "GeneralTitle",
        "content": "GENERAL information",
        "groupId": "faa47645-6887-ef11-8474-000d3a37e3b6",
        "position": 0,
        "area": "General"
      },
      {
        "type": "GeneralTitle",
        "content": "IMPORTANT TRANSFER INFORMATION",
        "groupId": "4b757445-6887-ef11-8474-000d3a37e3b6",
        "position": 2,
        "area": "General"
      }
    ],
    "articulations": [],
    "catalogYear": "{\"receivingCatalogYearBegin\":2025,\"receivingCatalogYearEnd\":2026,\"sendingCatalogYearBegin\":2025,\"sendingCatalogYearEnd\":2026}"
  },
  "validationFailure": null,
  "isSuccessful": true
}