{
  "result": {
    "name": "MUSIC, B.M. - Option in Percussion",
    "type": "Major",
    "publishDate": "2025-12-22T21:29:59.693832",
    "receivingInstitution": "{\"id\":42,\"code\":\"CSUN    \",\"isCommunityCollege\":false,\"category\":\"CSU\",\"termType\":\"Semester\",\"names\":[{\"name\":\"California State University, Northridge\",\"hasDepartments\":true,\"fromYear\":0,\"hideInList\":false}],\"termTypeAcademicYears\":[{\"termType\":\"Semester\",\"fromYear\":1980}],\"beginId\":31,\"endId\":null}",
    "sendingInstitution": "{\"id\":113,\"code\":\"DAC     \",\"isCommunityCollege\":true,\"category\":\"CCC\",\"termType\":\"Quarter\",\"names\":[{\"name\":\"De Anza College\",\"hasDepartments\":true,\"fromYear\":0,\"hideInList\":false}],\"termTypeAcademicYears\":[{\"termType\":\"Quarter\",\"fromYear\":1980}],\"beginId\":31,\"endId\":null}",
    "academicYear": "{\"id\":76,\"code\":\"2025-2026\",\"beginDate\":\"2025-10-01T00:00:00\",\"endDate\":\"2026-10-01T00:00:00\",\"isOpenForMaintenance\":true,\"isOpenForPublic\":true,\"isOpenForReporting\":true,\"isLocked\":false}",
    "templateAssets": [
      {
        "type": "GeneralText",
        "content": "<p><strong>This agreement displays all lower-division courses required in the major:</strong> CSU Northridge courses on the left, approved (articulated) transfer courses to the right. General education (Cal-GETC or CSU Northridge GE) and upper-division courses are also required to complete the bachelor's degree.</p><p><br></p><p>Completion of all coursework listed in this agreement is not mandatory prior to admission. For CSU Northridge Undergraduate <strong>Admission Requirements</strong>, refer to <a href=\"http://www.csun.edu/admissions-records/apply-upper-division-transfer-student#eligible\" rel=\"noopener noreferrer\" target=\"_blank\">Upper Division Transfer</a>.</p><p><br></p><p>Some coursework may be satisfied by Advanced Placement exams completed in high school. Visit <a href=\"http://catalog.csun.edu/policies/advanced-placement-ap-credit/\" rel=\"noopener noreferrer\" target=\"_blank\">AP Credit</a> for information. Additional information about the major is available in the <a href=\"http://catalog.csun.edu/programs/major/\" rel=\"noopener noreferrer\" target=\"_blank\">CSUN University Catalog</a>.</p><p><br></p><p>Questions regarding this agreement may be directed to: <a href=\"mailto:articulation@csun.edu\" rel=\"noopener noreferrer\" target=\"_blank\">articulation@csun.edu</a>.</p>",
        "groupId": "c9a86f45-6887-ef11-8474-000d3a37e3b6",
        "position": 2,
        "area": "General"
      },
      {
        "type": "GeneralTitle",
        "content": "Music, B.M. - General Information",
        "groupId": "b6a86f45-6887-ef11-8474-000d3a37e3b6",
        "position": 3,
        "area": "General"
      },
      {
        "type": "GeneralTitle",
        "content": "General Information",
        "groupId": "b8a86f45-6887-ef11-8474-000d3a37e3b6",
        "position": 1,
        "area": "General"
      },
      {
        "type": "GeneralText",
        "content": "<p>Admission to the major in Music for all undergraduate degrees is determined by audition. Audition procedures and standards are listed on the <a href=\"https://www.csun.edu/mike-curb-arts-media-communication/music/prospective-students/audition-placement\" rel=\"noopener noreferrer\" target=\"_blank\">Department of Music\u2014Audition and Placement</a> website.</p><p><br></p><p>Credit will be granted for lessons taken previously up to the skill level demonstrated. Maximum of 8 units of ensemble and 8 units of individual lessons will be accepted on transfer for the B.M., subject to placement testing.</p>",
        "groupId": "b9a86f45-6887-ef11-8474-000d3a37e3b6",
        "position": 4,
        "area": "General"
      },
      {
        "type": "RequirementGroup",
        "hideSectionLetters": false,
        "sections": [
          {
            "type": "Section",
            "rows": [
              {
                "position": 11,
                "cells": [
                  {
                    "type": "Course",
                    "course": {
                      "courseIdentifierParentId": 136902,
                      "courseTitle": "Harmony II",
                      "courseNumber": "214",
                      "prefix": "MUS",
                      "prefixParentId": 6549,
                      "prefixDescription": "Music",
                      "departmentParentId": 9406,
                      "department": "Music",
                      "begin": "F1999",
                      "end": "",
                      "minUnits": 3.0,
                      "maxUnits": 3.0,
                      "pathways": []
                    },
                    "visibleCrossListedCourses": [],
                    "requisites": [],
                    "courseAttributes": [],
                    "id": "046dd1c0-39dd-4afa-b5fe-08dda831fbfa",
                    "position": 0,
                    "attributes": []
                  }
                ],
                "attributes": []
              },
              {
                "position": 2,
                "cells": [
                  {
                    "type": "Series",
                    "series": {
                      "conjunction": "And",
                      "name": "MUS 112, MUS 112L",
                      "courses": [
                        {
                          "id": "1c09c97b-7f1b-48c2-b5ea-08dda831f292",
                          "position": 0,
                          "courseIdentifierParentId": 47629,
                          "courseTitle": "Musicianship II",
                          "courseNumber": "112",
                          "prefix": "MUS",
                          "prefixParentId": 6549,
                          "prefixDescription": "Music",
                          "departmentParentId": 9406,
                          "department": "Music",
                          "begin": "F1999",
                          "end": "",
                          "minUnits": 1.0,
                          "maxUnits": 1.0,
                          "pathways": []
                        },
                        {
                          "id": "35bab330-dd4d-4da0-b5eb-08dda831f292",
                          "position": 1,
                          "courseIdentifierParentId": 136576,
                          "courseTitle": "Musicianship II Lab",
                          "courseNumber": "112L",
                          "prefix": "MUS",
                          "prefixParentId": 6549,
                          "prefixDescription": "Music",
                          "departmentParentId": 9406,
                          "department": "Music",
                          "begin": "F1999",
                          "end": "",
                          "minUnits": 1.0,
                          "maxUnits": 1.0,
                          "pathways": []
                        }
                      ],
                      "seriesPathways": []
                    },
                    "requisites": [],
                    "visibleCrossListedCourses": [],
                    "seriesAttributes": [],
                    "courseAttributes": [
                      {
                        "seriesCourseId": "35bab330-dd4d-4da0-b5eb-08dda831f292",
                        "position": 0,
                        "content": "Articulation is subject to placement by proficiency exam"
                      }
                    ],
                    "id": "1cd53580-629f-4b6a-b5ff-08dda831fbfa",
                    "position": 0,
                    "attributes": []
                  }
                ],
                "attributes": []
              },
              {
                "position": 3,
                "cells": [
                  {
                    "type": "Series",
                    "series": {
                      "conjunction": "And",
                      "name": "MUS 191, MUS 191L",
                      "courses": [
                        {
                          "id": "d4264239-483a-4a04-b585-08dda831f292",
                          "position": 0,
                          "courseIdentifierParentId": 121137,
                          "courseTitle": "Fundamentals of Music Technology",
                          "courseNumber": "191",
                          "prefix": "MUS",
                          "prefixParentId": 6549,
                          "prefixDescription": "Music",
                          "departmentParentId": 9406,
                          "department": "Music",
                          "begin": "F1999",
                          "end": "",
                          "minUnits": 2.0,
                          "maxUnits": 2.0,
                          "pathways": []
                        },
                        {
                          "id": "0972f0ad-51bb-4829-b586-08dda831f292",
                          "position": 1,
                          "courseIdentifierParentId": 136559,
                          "courseTitle": "Fundamentals of Music Technology Lab",
                          "courseNumber": "191L",
                          "prefix": "MUS",
                          "prefixParentId": 6549,
                          "prefixDescription": "Music",
                          "departmentParentId": 9406,
                          "department": "Music",
                          "begin": "F1999",
                          "end": "",
                          "minUnits": 1.0,
                          "maxUnits": 1.0,
                          "pathways": []
                        }
                      ],
                      "seriesPathways": []
                    },
                    "requisites": [],
                    "visibleCrossListedCourses": [],
                    "seriesAttributes": [],
                    "courseAttributes": [],
                    "id": "6eaa7a15-7d92-4547-b600-08dda831fbfa",
                    "position": 0,
                    "attributes": []
                  }
                ],
                "attributes": []
              },
              {
                "position": 10,
                "cells": [
                  {
                    "type": "Course",
                    "course": {
                      "courseIdentifierParentId": 136876,
                      "courseTitle": "Harmony I",
                      "courseNumber": "213",
                      "prefix": "MUS",
                      "prefixParentId": 6549,
                      "prefixDescription": "Music",
                      "departmentParentId": 9406,
                      "department": "Music",
                      "begin": "F1999",
                      "end": "",
                      "minUnits": 3.0,
                      "maxUnits": 3.0,
                      "pathways": []
                    },
                    "visibleCrossListedCourses": [],
                    "requisites": [],
                    "courseAttributes": [],
                    "id": "886dcf37-5000-4f00-b601-08dda831fbfa",
                    "position": 0,
                    "attributes": []
                  }
                ],
                "attributes": []
              },
              {
                "position": 7,
                "cells": [
                  {
                    "type": "Course",
                    "course": {
                      "courseIdentifierParentId": 48398,
                      "courseTitle": "Keyboard Musicianship IV",
                      "courseNumber": "210B",
                      "prefix": "MUS",
                      "prefixParentId": 6549,
                      "prefixDescription": "Music",
                      "departmentParentId": 9406,
                      "department": "Music",
                      "begin": "F1999",
                      "end": "",
                      "minUnits": 1.0,
                      "maxUnits": 1.0,
                      "pathways": []
                    },
                    "visibleCrossListedCourses": [],
                    "requisites": [],
                    "courseAttributes": [
                      {
                        "position": 0,
                        "content": "Articulation is subject to placement by proficiency exam"
                      }
                    ],
                    "id": "598a7fcb-36d9-4afb-b602-08dda831fbfa",
                    "position": 0,
                    "attributes": []
                  }
                ],
                "attributes": []
              },
              {
                "position": 8,
                "cells": [
                  {
                    "type": "Series",
                    "series": {
                      "conjunction": "And",
                      "name": "MUS 211, MUS 211L",
                      "courses": [
                        {
                          "id": "3032ef45-c9bd-454b-b5c2-08dda831f292",
                          "position": 0,
                          "courseIdentifierParentId": 46045,
                          "courseTitle": "Musicianship III",
                          "courseNumber": "211",
                          "prefix": "MUS",
                          "prefixParentId": 6549,
                          "prefixDescription": "Music",
                          "departmentParentId": 9406,
                          "department": "Music",
                          "begin": "F1999",
                          "end": "",
                          "minUnits": 1.0,
                          "maxUnits": 1.0,
                          "pathways": []
                        },
                        {
                          "id": "fb04c7be-dd9a-4c8c-b5c3-08dda831f292",
                          "position": 1,
                          "courseIdentifierParentId": 136582,
                          "courseTitle": "Musicianship III Lab",
                          "courseNumber": "211L",
                          "prefix": "MUS",
                          "prefixParentId": 6549,
                          "prefixDescription": "Music",
                          "departmentParentId": 9406,
                          "department": "Music",
                          "begin": "F1999",
                          "end": "",
                          "minUnits": 1.0,
                          "maxUnits": 1.0,
                          "pathways": []
                        }
                      ],
                      "seriesPathways": []
                    },
                    "requisites": [],
                    "visibleCrossListedCourses": [],
                    "seriesAttributes": [],
                    "courseAttributes": [
                      {
                        "seriesCourseId": "fb04c7be-dd9a-4c8c-b5c3-08dda831f292",
                        "position": 0,
                        "content": "Articulation is subject to placement by proficiency exam"
                      }
                    ],
                    "id": "4ca06d85-da77-4619-b603-08dda831fbfa",
                    "position": 0,
                    "attributes": []
                  }
                ],
                "attributes": []
              },
              {
                "position": 4,
                "cells": [
                  {
                    "type": "Course",
                    "course": {
                      "courseIdentifierParentId": 331018,
                      "courseTitle": "Style/Literature of Western Music I",
                      "courseNumber": "201",
                      "prefix": "MUS",
                      "prefixParentId": 6549,
                      "prefixDescription": "Music",
                      "departmentParentId": 9406,
                      "department": "Music",
                      "begin": "F1999",
                      "end": "",
                      "minUnits": 3.0,
                      "maxUnits": 3.0,
                      "pathways": []
                    },
                    "visibleCrossListedCourses": [],
                    "requisites": [],
                    "courseAttributes": [],
                    "id": "9f41a560-d5a6-47cd-b604-08dda831fbfa",
                    "position": 0,
                    "attributes": []
                  }
                ],
                "attributes": []
              },
              {
                "position": 1,
                "cells": [
                  {
                    "type": "Course",
                    "course": {
                      "courseIdentifierParentId": 47307,
                      "courseTitle": "Keyboard Musicianship II",
                      "courseNumber": "110B",
                      "prefix": "MUS",
                      "prefixParentId": 6549,
                      "prefixDescription": "Music",
                      "departmentParentId": 9406,
                      "department": "Music",
                      "begin": "F1999",
                      "end": "",
                      "minUnits": 1.0,
                      "maxUnits": 1.0,
                      "pathways": []
                    },
                    "visibleCrossListedCourses": [],
                    "requisites": [],
                    "courseAttributes": [
                      {
                        "position": 0,
                        "content": "Articulation is subject to placement by proficiency exam"
                      }
                    ],
                    "id": "d00d3e8f-44a1-4c13-b605-08dda831fbfa",
                    "position": 0,
                    "attributes": []
                  }
                ],
                "attributes": []
              },
              {
                "position": 6,
                "cells": [
                  {
                    "type": "Course",
                    "course": {
                      "courseIdentifierParentId": 314603,
                      "courseTitle": "Keyboard Musicianship III",
                      "courseNumber": "210A",
                      "prefix": "MUS",
                      "prefixParentId": 6549,
                      "prefixDescription": "Music",
                      "departmentParentId": 9406,
                      "department": "Music",
                      "begin": "F1999",
                      "end": "",
                      "minUnits": 1.0,
                      "maxUnits": 1.0,
                      "pathways": []
                    },
                    "visibleCrossListedCourses": [],
                    "requisites": [],
                    "courseAttributes": [
                      {
                        "position": 0,
                        "content": "Articulation is subject to placement by proficiency exam"
                      }
                    ],
                    "id": "78914215-2bfd-4da8-b606-08dda831fbfa",
                    "position": 0,
                    "attributes": []
                  }
                ],
                "attributes": []
              },
              {
                "position": 5,
                "cells": [
                  {
                    "type": "Course",
                    "course": {
                      "courseIdentifierParentId": 331032,
                      "courseTitle": "Style/Literature of Western Music II",
                      "courseNumber": "202",
                      "prefix": "MUS",
                      "prefixParentId": 6549,
                      "prefixDescription": "Music",
                      "departmentParentId": 9406,
                      "department": "Music",
                      "begin": "F1999",
                      "end": "",
                      "minUnits": 3.0,
                      "maxUnits": 3.0,
                      "pathways": []
                    },
                    "visibleCrossListedCourses": [],
                    "requisites": [],
                    "courseAttributes": [],
                    "id": "738ffd16-443b-4161-b607-08dda831fbfa",
                    "position": 0,
                    "attributes": []
                  }
                ],
                "attributes": []
              },
              {
                "position": 9,
                "cells": [
                  {
                    "type": "Series",
                    "series": {
                      "conjunction": "And",
                      "name": "MUS 212, MUS 212L",
                      "courses": [
                        {
                          "id": "ae045e41-a523-4424-b5b4-08dda831f292",
                          "position": 0,
                          "courseIdentifierParentId": 45596,
                          "courseTitle": "Musicianship IV",
                          "courseNumber": "212",
                          "prefix": "MUS",
                          "prefixParentId": 6549,
                          "prefixDescription": "Music",
                          "departmentParentId": 9406,
                          "department": "Music",
                          "begin": "F1999",
                          "end": "",
                          "minUnits": 1.0,
                          "maxUnits": 1.0,
                          "pathways": []
                        },
                        {
                          "id": "7e5a2d11-625f-42c0-b5b5-08dda831f292",
                          "position": 1,
                          "courseIdentifierParentId": 47580,
                          "courseTitle": "Musicianship IV Lab",
                          "courseNumber": "212L",
                          "prefix": "MUS",
                          "prefixParentId": 6549,
                          "prefixDescription": "Music",
                          "departmentParentId": 9406,
                          "department": "Music",
                          "begin": "F1999",
                          "end": "",
                          "minUnits": 1.0,
                          "maxUnits": 1.0,
                          "pathways": []
                        }
                      ],
                      "seriesPathways": []
                    },
                    "requisites": [],
                    "visibleCrossListedCourses": [],
                    "seriesAttributes": [],
                    "courseAttributes": [
                      {
                        "seriesCourseId": "7e5a2d11-625f-42c0-b5b5-08dda831f292",
                        "position": 0,
                        "content": "Articulation is subject to placement by proficiency exam"
                      }
                    ],
                    "id": "a5cc5289-506e-4ad4-b608-08dda831fbfa",
                    "position": 0,
                    "attributes": []
                  }
                ],
                "attributes": []
              },
              {
                "position": 0,
                "cells": [
                  {
                    "type": "Course",
                    "course": {
                      "courseIdentifierParentId": 47590,
                      "courseTitle": "Keyboard Musicianship I",
                      "courseNumber": "110A",
                      "prefix": "MUS",
                      "prefixParentId": 6549,
                      "prefixDescription": "Music",
                      "departmentParentId": 9406,
                      "department": "Music",
                      "begin": "F1999",
                      "end": "",
                      "minUnits": 1.0,
                      "maxUnits": 1.0,
                      "pathways": []
                    },
                    "visibleCrossListedCourses": [],
                    "requisites": [],
                    "courseAttributes": [
                      {
                        "position": 0,
                        "content": "Articulation is subject to placement by proficiency exam"
                      }
                    ],
                    "id": "02b5db21-ae31-4fb1-b609-08dda831fbfa",
                    "position": 0,
                    "attributes": []
                  }
                ],
                "attributes": []
              }
            ],
            "advisements": [],
            "position": 0,
            "attributes": []
          }
        ],
        "attributes": [],
        "showConjunctionBetweenSections": false,
        "academicYearId": 0,
        "institutionParentId": 0,
        "instruction": null,
        "advisements": [],
        "groupId": "bba86f45-6887-ef11-8474-000d3a37e3b6",
        "position": 1,
        "area": "Requirements"
      },
      {
        "type": "RequirementTitle",
        "content": "LOWER DIVISION MAJOR PREPARATION COURSES",
        "groupId": "1a1a7745-6887-ef11-8474-000d3a37e3b6",
        "position": 0,
        "area": "Requirements"
      }
    ],
    "articulations": [],
    "catalogYear": "{\"receivingCatalogYearBegin\":2025,\"receivingCatalogYearEnd\":2026,\"sendingCatalogYearBegin\":2025,\"sendingCatalogYearEnd\":2026}"
  },
  "validationFailure": null,
  "isSuccessful": true
}