{
  "result": {
    "name": "Liberal Studies, B.A.",
    "type": "Major",
    "publishDate": "2025-07-29T23:47:03.3272249",
    "receivingInstitution": "{\"id\":129,\"code\":\"CSUFULL \",\"isCommunityCollege\":false,\"category\":\"CSU\",\"termType\":\"Semester\",\"names\":[{\"name\":\"California State University, Fullerton\",\"hasDepartments\":true,\"fromYear\":0,\"hideInList\":false}],\"termTypeAcademicYears\":[{\"termType\":\"Semester\",\"fromYear\":1980}],\"beginId\":31,\"endId\":null}",
    "sendingInstitution": "{\"id\":113,\"code\":\"DAC     \",\"isCommunityCollege\":true,\"category\":\"CCC\",\"termType\":\"Quarter\",\"names\":[{\"name\":\"De Anza College\",\"hasDepartments\":true,\"fromYear\":0,\"hideInList\":false}],\"termTypeAcademicYears\":[{\"termType\":\"Quarter\",\"fromYear\":1980}],\"beginId\":31,\"endId\":null}",
    "academicYear": "{\"id\":76,\"code\":\"2025-2026\",\"beginDate\":\"2025-10-01T00:00:00\",\"endDate\":\"2026-10-01T00:00:00\",\"isOpenForMaintenance\":true,\"isOpenForPublic\":true,\"isOpenForReporting\":true,\"isLocked\":false}",
    "templateAssets": [
      {
        "type": "GeneralText",
        "content": "<blockquote><span style=\"font-size: 12px;\">See the </span><a href=\"https://catalog.fullerton.edu/\" rel=\"noopener noreferrer\" target=\"_blank\" style=\"font-size: 12px;\">University Catalog</a><span style=\"font-size: 12px;\"> for the full listing of degree requirements for this major. </span></blockquote><blockquote><span style=\"font-size: 12px;\">See the Admissions website for </span><a href=\"https://admissions.fullerton.edu/prospectivestudent/transferlocaladmissionarea.php\" rel=\"noopener noreferrer\" target=\"_blank\" style=\"font-size: 12px;\">transfer admission requirements</a><span style=\"font-size: 12px;\"> &amp; </span><a href=\"https://admissions.fullerton.edu/deadlines/index.php\" rel=\"noopener noreferrer\" target=\"_blank\" style=\"font-size: 12px;\">Admissions deadlines</a></blockquote><blockquote><span style=\"font-size: 12px;\">See </span><a href=\"https://www.fullerton.edu/undergraduate/general-education/approved-courses.html#box5\" rel=\"noopener noreferrer\" target=\"_blank\" style=\"font-size: 12px;\">approved General Education </a><span style=\"font-size: 12px;\">courses at CSU Fullerton. </span></blockquote><blockquote><span style=\"font-size: 12px;\">See </span><a href=\"https://www.calstate.edu/apply/transfer/Pages/associate-degree-for-transfer-major-and-campus-search.aspx\" rel=\"noopener noreferrer\" target=\"_blank\" style=\"font-size: 12px;\">Associate Degree for Transfer.</a><span style=\"font-size: 12px;\"> </span></blockquote><blockquote><span style=\"font-size: 12px;\">See the </span><a href=\"https://www.calstate.edu/attend/student-services/casper/Pages/external-exam-credit.aspx\" rel=\"noopener noreferrer\" target=\"_blank\" style=\"font-size: 12px;\">Credit by Exam information (AP, IB, CLEP).</a></blockquote>",
        "groupId": "6d826f45-6887-ef11-8474-000d3a37e3b6",
        "position": 1,
        "area": "General"
      },
      {
        "type": "GeneralTitle",
        "content": "CSUF General Transfer Information",
        "groupId": "6f826f45-6887-ef11-8474-000d3a37e3b6",
        "position": 0,
        "area": "General"
      },
      {
        "type": "GeneralTitle",
        "content": "About This Major",
        "groupId": "71826f45-6887-ef11-8474-000d3a37e3b6",
        "position": 2,
        "area": "General"
      },
      {
        "type": "GeneralText",
        "content": "<p><strong>(120 UNITS)</strong></p><p>The Bachelor of Arts in Liberal Studies (<a href=\"https://catalog.fullerton.edu/preview_program.php?catoid=95&amp;poid=44767&amp;returnto=14173\" rel=\"noopener noreferrer\" target=\"_blank\">Link</a>) offers an interdisciplinary education in the arts and humanities, social sciences and natural sciences, together with rigorous training in critical thinking and argumentative writing. It thus establishes a secure foundation for any profession that requires general knowledge and prizes independent and creative thought. The program\u2019s graduates have been successful in education, law, management, non-profit and various entrepreneurial activities. Liberal Studies very effectively prepares students to obtain a multiple subject teaching credential and to pursue a variety of graduate degrees. Forming a diverse community and taking multiple perspectives, Liberal Studies students become well-rounded persons and life-long learners.</p><p><br></p><p><strong>Sequence of Core Courses</strong></p><p>Because the core curriculum is designed as an integrated whole and builds upon the student\u2019s general education, there is an order in which these courses need to be taken and there are certain prerequisites for them.&nbsp;LBST 300&nbsp;and&nbsp;LBST 302A/LBST 302B&nbsp;come first.&nbsp;LBST 302A&nbsp;is a prerequisite for&nbsp;LBST 302B.</p><p><br></p><p>LBST 302B&nbsp;and&nbsp;LBST 301&nbsp;are prerequisites for&nbsp;LBST 303,&nbsp;LBST 304,&nbsp;LBST 305.</p><p><br></p><p>LBST 401&nbsp;and the Senior Seminar come last.&nbsp;LBST 401&nbsp;requires the completion of&nbsp;LBST 304&nbsp;and either&nbsp;LBST 303&nbsp;or&nbsp;LBST 305. The Senior Seminar requires senior standing and 90 units of college work.</p><p><br></p><p><strong>Elementary Education Emphasis (21 units):</strong></p><p>The Elementary Education Emphasis requires courses from Visual and Performing Arts (3 units), Language and Literature (3 units), Mathematics and Natural Sciences (6 units), Social Sciences (3 units), and Cultural Diversity (3 units). Additionally, one upper-division course (3 units) from Biological Science, Chemistry and Biochemistry, Geology, Mathematics, Physics or from any department or program in the Arts and Humanities or Social Science and Cultural Diversity categories is required as an elective.&nbsp;MATH 303A&nbsp;is highly recommended. Please visit the catalog for more information.</p><p><br></p><p><strong>Interdisciplinary Thematic Emphasis (21 units):</strong></p><p>The Interdisciplinary Thematic Emphasis (ITE) is designed for students who have broad interests that expand beyond the confines of a single department. For these students, the ability to construct their own area of interdisciplinary study by taking advanced coursework in several disciplines may be more beneficial than restricting their study to one of the various majors offered by the university. The Interdisciplinary Thematic Emphasis does not duplicate any existing major. It is a well-thought-out, highly individualized group of courses that, even though they come from various departments, have a common subject, focus or interest.</p><ul><li><strong>Personalized Coordinated Program: </strong>In consultation with a Liberal Studies adviser, ITE students select 18 units of upper-division coursework from various departments for the purpose of pursuing an interdisciplinary problem, theme or issue. To ensure breadth of knowledge, ITE students are allowed to take: (a) no more than nine units from a single department; and (b) no more than 15 units from a single area of knowledge (humanities and arts, science, social sciences). ITE students must have their study plan approved by a Liberal Studies adviser prior to taking coursework.</li><li><strong>Senior Project: </strong>To integrate and synthesize knowledge acquired through their Personalized Coordinated Program, ITE students must complete a senior project (such as a thesis or a creative work relevant to the theme of their Personalized Coordinated Program) by enrolling in&nbsp;LBST 482&nbsp;or three units of&nbsp;LBST 499&nbsp;with a professor of their choice. ITE students should schedule an appointment with a LBST adviser immediately after deciding upon the thematic Emphasis in order to organize a project and enroll in the required units of&nbsp;LBST 482&nbsp;or&nbsp;LBST 499.</li></ul><p><br></p><p>ITE students may center their coursework on an academic interest or may select courses that prepare them for later professional training or for specific careers.</p><p><br></p><p><br></p><p><br></p><p>CSUF ENGL 211 (C-ID ENGL 160)</p><p>CSUF POSC 100 (C-ID POLS 110)</p>",
        "groupId": "73826f45-6887-ef11-8474-000d3a37e3b6",
        "position": 3,
        "area": "General"
      },
      {
        "type": "GeneralText",
        "content": "<p><a href=\"https://www.calstate.edu/apply/transfer/Pages/transfer-success-pathway.aspx\" rel=\"noopener noreferrer\" target=\"_blank\">Transfer Success Pathway</a> major eligible </p>",
        "groupId": "75826f45-6887-ef11-8474-000d3a37e3b6",
        "position": 4,
        "area": "General"
      },
      {
        "type": "RequirementTitle",
        "content": "ELEMENTARY EDUCATION EMPHASIS",
        "groupId": "c8a87645-6887-ef11-8474-000d3a37e3b6",
        "position": 2,
        "area": "Requirements"
      },
      {
        "type": "RequirementGroup",
        "hideSectionLetters": false,
        "sections": [
          {
            "type": "Section",
            "rows": [
              {
                "position": 0,
                "cells": [
                  {
                    "type": "Course",
                    "course": {
                      "courseIdentifierParentId": 240000,
                      "courseTitle": "Introduction to Language Structure and Language Use",
                      "courseNumber": "206",
                      "prefix": "ENGL",
                      "prefixParentId": 2753,
                      "prefixDescription": "English",
                      "departmentParentId": 5170,
                      "department": "English, Comparative Literature and Linguistics",
                      "begin": "F2021",
                      "end": "",
                      "minUnits": 3.0,
                      "maxUnits": 3.0,
                      "pathways": []
                    },
                    "visibleCrossListedCourses": [
                      {
                        "course": {
                          "courseIdentifierParentId": 240001,
                          "courseTitle": "Introduction to Language Structure and Language Use",
                          "courseNumber": "206",
                          "prefix": "LING",
                          "prefixParentId": 2583,
                          "prefixDescription": "Linguistics",
                          "departmentParentId": 8643,
                          "department": "Linguistics",
                          "begin": "F2021",
                          "end": "",
                          "minUnits": 3.0,
                          "maxUnits": 3.0,
                          "pathways": []
                        }
                      }
                    ],
                    "requisites": [],
                    "courseAttributes": [
                      {
                        "position": 0,
                        "content": "Minimum grade required: C or better"
                      }
                    ],
                    "id": "b116d3c2-d836-4e84-2e10-08dd55dbff36",
                    "position": 0,
                    "attributes": []
                  }
                ],
                "attributes": []
              },
              {
                "position": 1,
                "cells": [
                  {
                    "type": "Course",
                    "course": {
                      "courseIdentifierParentId": 136250,
                      "courseTitle": "British Literature to 1760",
                      "courseNumber": "211",
                      "prefix": "ENGL",
                      "prefixParentId": 2753,
                      "prefixDescription": "English",
                      "departmentParentId": 5170,
                      "department": "English, Comparative Literature and Linguistics",
                      "begin": "F2021",
                      "end": "",
                      "minUnits": 3.0,
                      "maxUnits": 3.0,
                      "pathways": []
                    },
                    "visibleCrossListedCourses": [],
                    "requisites": [],
                    "courseAttributes": [],
                    "id": "b1798069-ecbe-48ed-adf1-08dd89a43052",
                    "position": 0,
                    "attributes": []
                  }
                ],
                "attributes": []
              },
              {
                "position": 2,
                "cells": [
                  {
                    "type": "Course",
                    "course": {
                      "courseIdentifierParentId": 135273,
                      "courseTitle": "British Literature from 1760",
                      "courseNumber": "212",
                      "prefix": "ENGL",
                      "prefixParentId": 2753,
                      "prefixDescription": "English",
                      "departmentParentId": 5170,
                      "department": "English, Comparative Literature and Linguistics",
                      "begin": "F2021",
                      "end": "",
                      "minUnits": 3.0,
                      "maxUnits": 3.0,
                      "pathways": []
                    },
                    "visibleCrossListedCourses": [],
                    "requisites": [],
                    "courseAttributes": [],
                    "id": "76222f69-2924-4445-adf2-08dd89a43052",
                    "position": 0,
                    "attributes": []
                  }
                ],
                "attributes": []
              },
              {
                "position": 3,
                "cells": [
                  {
                    "type": "Course",
                    "course": {
                      "courseIdentifierParentId": 135271,
                      "courseTitle": "American Literature to Whitman",
                      "courseNumber": "221",
                      "prefix": "ENGL",
                      "prefixParentId": 2753,
                      "prefixDescription": "English",
                      "departmentParentId": 5170,
                      "department": "English, Comparative Literature and Linguistics",
                      "begin": "F2021",
                      "end": "",
                      "minUnits": 3.0,
                      "maxUnits": 3.0,
                      "pathways": []
                    },
                    "visibleCrossListedCourses": [],
                    "requisites": [],
                    "courseAttributes": [],
                    "id": "25934842-8479-409e-adf3-08dd89a43052",
                    "position": 0,
                    "attributes": []
                  }
                ],
                "attributes": []
              },
              {
                "position": 4,
                "cells": [
                  {
                    "type": "Course",
                    "course": {
                      "courseIdentifierParentId": 243035,
                      "courseTitle": "American Literature from Twain to the Moderns",
                      "courseNumber": "222",
                      "prefix": "ENGL",
                      "prefixParentId": 2753,
                      "prefixDescription": "English",
                      "departmentParentId": 5170,
                      "department": "English, Comparative Literature and Linguistics",
                      "begin": "F2021",
                      "end": "",
                      "minUnits": 3.0,
                      "maxUnits": 3.0,
                      "pathways": []
                    },
                    "visibleCrossListedCourses": [],
                    "requisites": [],
                    "courseAttributes": [],
                    "id": "982021f1-96e6-433e-adf4-08dd89a43052",
                    "position": 0,
                    "attributes": []
                  }
                ],
                "attributes": []
              },
              {
                "position": 5,
                "cells": [
                  {
                    "type": "Course",
                    "course": {
                      "courseIdentifierParentId": 145527,
                      "courseTitle": "Children's Literature",
                      "courseNumber": "341",
                      "prefix": "ENGL",
                      "prefixParentId": 2753,
                      "prefixDescription": "English",
                      "departmentParentId": 5170,
                      "department": "English, Comparative Literature and Linguistics",
                      "begin": "S2003",
                      "end": "",
                      "minUnits": 3.0,
                      "maxUnits": 3.0,
                      "pathways": []
                    },
                    "visibleCrossListedCourses": [],
                    "requisites": [],
                    "courseAttributes": [],
                    "id": "847c3ded-c3e6-4c85-adf5-08dd89a43052",
                    "position": 0,
                    "attributes": [
                      {
                        "position": 0,
                        "content": "No upper division credit"
                      }
                    ]
                  }
                ],
                "attributes": []
              }
            ],
            "advisements": [
              {
                "type": "NFollowing",
                "amount": 1.0,
                "amountUnitType": "Course",
                "position": 0,
                "selectionType": "Complete"
              }
            ],
            "position": 1,
            "attributes": []
          },
          {
            "type": "SectionHeader",
            "content": "LANGUAGE AND LITERATURE",
            "position": 0,
            "attributes": []
          },
          {
            "type": "SectionHeader",
            "content": "MATHEMATICS AND SCIENCE COURSES",
            "position": 2,
            "attributes": []
          },
          {
            "type": "Section",
            "rows": [
              {
                "position": 0,
                "cells": [
                  {
                    "type": "Course",
                    "course": {
                      "courseIdentifierParentId": 367072,
                      "courseTitle": "Fundamental Concepts of Elementary Mathematics",
                      "courseNumber": "303B",
                      "prefix": "MATH",
                      "prefixParentId": 10041,
                      "prefixDescription": "Mathematics",
                      "departmentParentId": 9055,
                      "department": "Mathematics",
                      "begin": "F2015",
                      "end": "",
                      "minUnits": 3.0,
                      "maxUnits": 3.0,
                      "pathways": []
                    },
                    "visibleCrossListedCourses": [],
                    "requisites": [],
                    "courseAttributes": [],
                    "id": "7b604c7f-eba0-401f-adf0-08dd89a43052",
                    "position": 0,
                    "attributes": [
                      {
                        "position": 0,
                        "content": "No upper division credit"
                      }
                    ]
                  }
                ],
                "attributes": []
              }
            ],
            "advisements": [],
            "position": 3,
            "attributes": []
          }
        ],
        "attributes": [],
        "showConjunctionBetweenSections": false,
        "academicYearId": 0,
        "institutionParentId": 0,
        "instruction": {
          "type": "Conjunction",
          "conjunction": "And",
          "id": "e6958aee-f9aa-433e-570b-08dd55dbff42",
          "selectionType": "Complete"
        },
        "advisements": [],
        "groupId": "77826f45-6887-ef11-8474-000d3a37e3b6",
        "position": 3,
        "area": "Requirements"
      },
      {
        "type": "RequirementTitle",
        "content": "CORE COURSES",
        "groupId": "22717445-6887-ef11-8474-000d3a37e3b6",
        "position": 0,
        "area": "Requirements"
      },
      {
        "type": "RequirementGroup",
        "hideSectionLetters": false,
        "sections": [
          {
            "type": "Section",
            "rows": [
              {
                "position": 0,
                "cells": [
                  {
                    "type": "Course",
                    "course": {
                      "courseIdentifierParentId": 338397,
                      "courseTitle": "American Government",
                      "courseNumber": "100",
                      "prefix": "POSC",
                      "prefixParentId": 2042,
                      "prefixDescription": "Political Science",
                      "departmentParentId": 11050,
                      "department": "Political Science",
                      "begin": "F1995",
                      "end": "",
                      "minUnits": 3.0,
                      "maxUnits": 3.0,
                      "pathways": []
                    },
                    "visibleCrossListedCourses": [],
                    "requisites": [],
                    "courseAttributes": [],
                    "id": "9c3e2288-d0ce-4560-2e11-08dd55dbff36",
                    "position": 0,
                    "attributes": []
                  }
                ],
                "attributes": []
              }
            ],
            "advisements": [],
            "position": 0,
            "attributes": []
          }
        ],
        "attributes": [],
        "showConjunctionBetweenSections": false,
        "academicYearId": 0,
        "institutionParentId": 0,
        "instruction": null,
        "advisements": [],
        "groupId": "79826f45-6887-ef11-8474-000d3a37e3b6",
        "position": 5,
        "area": "Requirements"
      },
      {
        "type": "RequirementTitle",
        "content": "REQUIRED FOR GRADUATION",
        "groupId": "56387945-6887-ef11-8474-000d3a37e3b6",
        "position": 4,
        "area": "Requirements"
      },
      {
        "type": "RequirementGroup",
        "hideSectionLetters": false,
        "sections": [
          {
            "type": "Section",
            "rows": [
              {
                "position": 0,
                "cells": [
                  {
                    "type": "Course",
                    "course": {
                      "courseIdentifierParentId": 250278,
                      "courseTitle": "Introduction to the Humanities",
                      "courseNumber": "100",
                      "prefix": "LBST",
                      "prefixParentId": 5363,
                      "prefixDescription": "Liberal Studies",
                      "departmentParentId": 8456,
                      "department": "Liberal Studies",
                      "begin": "F2021",
                      "end": "",
                      "minUnits": 3.0,
                      "maxUnits": 3.0,
                      "pathways": []
                    },
                    "visibleCrossListedCourses": [],
                    "requisites": [],
                    "courseAttributes": [],
                    "id": "d8dba264-f595-476e-2e12-08dd55dbff36",
                    "position": 0,
                    "attributes": []
                  }
                ],
                "attributes": []
              },
              {
                "position": 1,
                "cells": [
                  {
                    "type": "Course",
                    "course": {
                      "courseIdentifierParentId": 252251,
                      "courseTitle": "Introduction to the Social Sciences",
                      "courseNumber": "101",
                      "prefix": "LBST",
                      "prefixParentId": 5363,
                      "prefixDescription": "Liberal Studies",
                      "departmentParentId": 8456,
                      "department": "Liberal Studies",
                      "begin": "F2021",
                      "end": "",
                      "minUnits": 3.0,
                      "maxUnits": 3.0,
                      "pathways": []
                    },
                    "visibleCrossListedCourses": [],
                    "requisites": [],
                    "courseAttributes": [],
                    "id": "48d38450-8d02-4203-2e13-08dd55dbff36",
                    "position": 0,
                    "attributes": []
                  }
                ],
                "attributes": []
              },
              {
                "position": 2,
                "cells": [
                  {
                    "type": "Course",
                    "course": {
                      "courseIdentifierParentId": 196717,
                      "courseTitle": "Introduction to Liberal Studies",
                      "courseNumber": "300",
                      "prefix": "LBST",
                      "prefixParentId": 5363,
                      "prefixDescription": "Liberal Studies",
                      "departmentParentId": 8456,
                      "department": "Liberal Studies",
                      "begin": "F2021",
                      "end": "",
                      "minUnits": 3.0,
                      "maxUnits": 3.0,
                      "pathways": []
                    },
                    "visibleCrossListedCourses": [],
                    "requisites": [],
                    "courseAttributes": [],
                    "id": "9a923107-f1ad-434f-2e14-08dd55dbff36",
                    "position": 0,
                    "attributes": []
                  }
                ],
                "attributes": []
              }
            ],
            "advisements": [],
            "position": 0,
            "attributes": []
          }
        ],
        "attributes": [],
        "showConjunctionBetweenSections": false,
        "academicYearId": 0,
        "institutionParentId": 0,
        "instruction": {
          "type": "Following",
          "id": "3b8b7bac-7b38-44ed-570c-08dd55dbff42",
          "selectionType": "Complete"
        },
        "advisements": [],
        "groupId": "fcc86f45-6887-ef11-8474-000d3a37e3b6",
        "position": 1,
        "area": "Requirements"
      },
      {
        "type": "RequirementTitle",
        "content": "ARTICULATION DETAILS",
        "groupId": "51777445-6887-ef11-8474-000d3a37e3b6",
        "position": 6,
        "area": "Requirements"
      }
    ],
    "articulations": [
      {
        "templateCellId": "b1798069-ecbe-48ed-adf1-08dd89a43052",
        "articulation": {
          "type": "Course",
          "course": {
            "courseIdentifierParentId": 136250,
            "courseTitle": "British Literature to 1760",
            "courseNumber": "211",
            "prefix": "ENGL",
            "prefixParentId": 2753,
            "prefixDescription": "English",
            "departmentParentId": 5170,
            "department": "English, Comparative Literature and Linguistics",
            "begin": "F2021",
            "end": "",
            "minUnits": 3.0,
            "maxUnits": 3.0,
            "pathways": []
          },
          "visibleCrossListedCourses": [],
          "courseAttributes": [],
          "sendingArticulation": {
            "noArticulationReason": null,
            "deniedCourses": [],
            "items": [
              {
                "courseConjunction": "And",
                "items": [
                  {
                    "visibleCrossListedCourses": [],
                    "requisites": [],
                    "attributes": [],
                    "courseIdentifierParentId": 363594,
                    "courseTitle": "Major British Writers (Medieval and Renaissance) - HONORS",
                    "courseNumber": "46AH",
                    "prefix": "ELIT",
                    "prefixParentId": 4816,
                    "prefixDescription": "English (Literature)",
                    "departmentParentId": 5069,
                    "department": "English (Literature)",
                    "begin": "F2018",
                    "end": "",
                    "minUnits": 4.0,
                    "maxUnits": 4.0,
                    "pathways": [],
                    "publishedCourseIdentifierYearTermId": null,
                    "position": 0,
                    "type": "Course"
                  },
                  {
                    "visibleCrossListedCourses": [],
                    "requisites": [],
                    "attributes": [],
                    "courseIdentifierParentId": 363600,
                    "courseTitle": "Major British Writers (Neo-Classical and Romantic) - HONORS",
                    "courseNumber": "46BH",
                    "prefix": "ELIT",
                    "prefixParentId": 4816,
                    "prefixDescription": "English (Literature)",
                    "departmentParentId": 5069,
                    "department": "English (Literature)",
                    "begin": "F2018",
                    "end": "",
                    "minUnits": 4.0,
                    "maxUnits": 4.0,
                    "pathways": [],
                    "publishedCourseIdentifierYearTermId": null,
                    "position": 1,
                    "type": "Course"
                  }
                ],
                "attributes": [],
                "position": 1,
                "type": "CourseGroup"
              },
              {
                "courseConjunction": "And",
                "items": [
                  {
                    "visibleCrossListedCourses": [],
                    "requisites": [],
                    "attributes": [],
                    "courseIdentifierParentId": 353362,
                    "courseTitle": "Major British Writers (Medieval and Renaissance)",
                    "courseNumber": "46A",
                    "prefix": "ELIT",
                    "prefixParentId": 4816,
                    "prefixDescription": "English (Literature)",
                    "departmentParentId": 5069,
                    "department": "English (Literature)",
                    "begin": "F1999",
                    "end": "",
                    "minUnits": 4.0,
                    "maxUnits": 4.0,
                    "pathways": [],
                    "publishedCourseIdentifierYearTermId": null,
                    "position": 0,
                    "type": "Course"
                  },
                  {
                    "visibleCrossListedCourses": [],
                    "requisites": [],
                    "attributes": [],
                    "courseIdentifierParentId": 289056,
                    "courseTitle": "Major British Writers (Neo-Classical and Romantic)",
                    "courseNumber": "46B",
                    "prefix": "ELIT",
                    "prefixParentId": 4816,
                    "prefixDescription": "English (Literature)",
                    "departmentParentId": 5069,
                    "department": "English (Literature)",
                    "begin": "F1999",
                    "end": "",
                    "minUnits": 4.0,
                    "maxUnits": 4.0,
                    "pathways": [],
                    "publishedCourseIdentifierYearTermId": null,
                    "position": 1,
                    "type": "Course"
                  }
                ],
                "attributes": [],
                "position": 0,
                "type": "CourseGroup"
              }
            ],
            "courseGroupConjunctions": [],
            "type": "SendingArticulation",
            "attributes": []
          },
          "templateOverrides": [],
          "attributes": [],
          "receivingAttributes": []
        },
        "receivingAttributes": {
          "type": "Course",
          "courseAttributes": [],
          "attributes": []
        }
      },
      {
        "templateCellId": "76222f69-2924-4445-adf2-08dd89a43052",
        "articulation": {
          "type": "Course",
          "course": {
            "courseIdentifierParentId": 135273,
            "courseTitle": "British Literature from 1760",
            "courseNumber": "212",
            "prefix": "ENGL",
            "prefixParentId": 2753,
            "prefixDescription": "English",
            "departmentParentId": 5170,
            "department": "English, Comparative Literature and Linguistics",
            "begin": "F2021",
            "end": "",
            "minUnits": 3.0,
            "maxUnits": 3.0,
            "pathways": []
          },
          "visibleCrossListedCourses": [],
          "courseAttributes": [],
          "sendingArticulation": {
            "noArticulationReason": null,
            "deniedCourses": [],
            "items": [
              {
                "courseConjunction": "And",
                "items": [
                  {
                    "visibleCrossListedCourses": [],
                    "requisites": [],
                    "attributes": [],
                    "courseIdentifierParentId": 363600,
                    "courseTitle": "Major British Writers (Neo-Classical and Romantic) - HONORS",
                    "courseNumber": "46BH",
                    "prefix": "ELIT",
                    "prefixParentId": 4816,
                    "prefixDescription": "English (Literature)",
                    "departmentParentId": 5069,
                    "department": "English (Literature)",
                    "begin": "F2018",
                    "end": "",
                    "minUnits": 4.0,
                    "maxUnits": 4.0,
                    "pathways": [],
                    "publishedCourseIdentifierYearTermId": null,
                    "position": 0,
                    "type": "Course"
                  },
                  {
                    "visibleCrossListedCourses": [],
                    "requisites": [],
                    "attributes": [],
                    "courseIdentifierParentId": 363601,
                    "courseTitle": "Major British Writers (Victorian and Modern) - HONORS",
                    "courseNumber": "46CH",
                    "prefix": "ELIT",
                    "prefixParentId": 4816,
                    "prefixDescription": "English (Literature)",
                    "departmentParentId": 5069,
                    "department": "English (Literature)",
                    "begin": "F2018",
                    "end": "",
                    "minUnits": 4.0,
                    "maxUnits": 4.0,
                    "pathways": [],
                    "publishedCourseIdentifierYearTermId": null,
                    "position": 1,
                    "type": "Course"
                  }
                ],
                "attributes": [],
                "position": 1,
                "type": "CourseGroup"
              },
              {
                "courseConjunction": "And",
                "items": [
                  {
                    "visibleCrossListedCourses": [],
                    "requisites": [],
                    "attributes": [],
                    "courseIdentifierParentId": 289056,
                    "courseTitle": "Major British Writers (Neo-Classical and Romantic)",
                    "courseNumber": "46B",
                    "prefix": "ELIT",
                    "prefixParentId": 4816,
                    "prefixDescription": "English (Literature)",
                    "departmentParentId": 5069,
                    "department": "English (Literature)",
                    "begin": "F1999",
                    "end": "",
                    "minUnits": 4.0,
                    "maxUnits": 4.0,
                    "pathways": [],
                    "publishedCourseIdentifierYearTermId": null,
                    "position": 0,
                    "type": "Course"
                  },
                  {
                    "visibleCrossListedCourses": [],
                    "requisites": [],
                    "attributes": [],
                    "courseIdentifierParentId": 253834,
                    "courseTitle": "Major British Writers (Victorian and Modern)",
                    "courseNumber": "46C",
                    "prefix": "ELIT",
                    "prefixParentId": 4816,
                    "prefixDescription": "English (Literature)",
                    "departmentParentId": 5069,
                    "department": "English (Literature)",
                    "begin": "F1999",
                    "end": "",
                    "minUnits": 4.0,
                    "maxUnits": 4.0,
                    "pathways": [],
                    "publishedCourseIdentifierYearTermId": null,
                    "position": 1,
                    "type": "Course"
                  }
                ],
                "attributes": [],
                "position": 0,
                "type": "CourseGroup"
              }
            ],
            "courseGroupConjunctions": [
              {
                "id": "0d0b8e47-1f42-49a4-cde0-08dd55dc249c",
                "sendingArticulationId": "ab0364fe-e341-43e5-6b64-08dd55dc242e",
                "groupConjunction": "Or",
                "sendingCourseGroupBeginPosition": 0,
                "sendingCourseGroupEndPosition": 1
              }
            ],
            "type": "SendingArticulation",
            "attributes": []
          },
          "templateOverrides": [],
          "attributes": [],
          "receivingAttributes": []
        },
        "receivingAttributes": {
          "type": "Course",
          "courseAttributes": [],
          "attributes": []
        }
      },
      {
        "templateCellId": "25934842-8479-409e-adf3-08dd89a43052",
        "articulation": {
          "type": "Course",
          "course": {
            "courseIdentifierParentId": 135271,
            "courseTitle": "American Literature to Whitman",
            "courseNumber": "221",
            "prefix": "ENGL",
            "prefixParentId": 2753,
            "prefixDescription": "English",
            "departmentParentId": 5170,
            "department": "English, Comparative Literature and Linguistics",
            "begin": "F2021",
            "end": "",
            "minUnits": 3.0,
            "maxUnits": 3.0,
            "pathways": []
          },
          "visibleCrossListedCourses": [],
          "courseAttributes": [],
          "sendingArticulation": {
            "noArticulationReason": null,
            "deniedCourses": [],
            "items": [
              {
                "courseConjunction": "And",
                "items": [
                  {
                    "visibleCrossListedCourses": [],
                    "requisites": [],
                    "attributes": [],
                    "courseIdentifierParentId": 353683,
                    "courseTitle": "Major American Writers (Colonial and Romantic, 1620-1865)",
                    "courseNumber": "48A",
                    "prefix": "ELIT",
                    "prefixParentId": 4816,
                    "prefixDescription": "English (Literature)",
                    "departmentParentId": 5069,
                    "department": "English (Literature)",
                    "begin": "F2010",
                    "end": "",
                    "minUnits": 4.0,
                    "maxUnits": 4.0,
                    "pathways": [],
                    "publishedCourseIdentifierYearTermId": null,
                    "position": 0,
                    "type": "Course"
                  },
                  {
                    "visibleCrossListedCourses": [],
                    "requisites": [],
                    "attributes": [],
                    "courseIdentifierParentId": 353308,
                    "courseTitle": "Major American Writers (The Advent of Realism, 1865-1914)",
                    "courseNumber": "48B",
                    "prefix": "ELIT",
                    "prefixParentId": 4816,
                    "prefixDescription": "English (Literature)",
                    "departmentParentId": 5069,
                    "department": "English (Literature)",
                    "begin": "F2010",
                    "end": "",
                    "minUnits": 4.0,
                    "maxUnits": 4.0,
                    "pathways": [],
                    "publishedCourseIdentifierYearTermId": null,
                    "position": 1,
                    "type": "Course"
                  }
                ],
                "attributes": [],
                "position": 0,
                "type": "CourseGroup"
              },
              {
                "courseConjunction": "And",
                "items": [
                  {
                    "visibleCrossListedCourses": [],
                    "requisites": [],
                    "attributes": [],
                    "courseIdentifierParentId": 363728,
                    "courseTitle": "Major American Writers (Colonial to Romantic, 1620-1865) - HONORS",
                    "courseNumber": "48AH",
                    "prefix": "ELIT",
                    "prefixParentId": 4816,
                    "prefixDescription": "English (Literature)",
                    "departmentParentId": 5069,
                    "department": "English (Literature)",
                    "begin": "F2018",
                    "end": "",
                    "minUnits": 4.0,
                    "maxUnits": 4.0,
                    "pathways": [],
                    "publishedCourseIdentifierYearTermId": null,
                    "position": 0,
                    "type": "Course"
                  },
                  {
                    "visibleCrossListedCourses": [],
                    "requisites": [],
                    "attributes": [],
                    "courseIdentifierParentId": 363729,
                    "courseTitle": "Major American Writers (The Advent of Realism, 1865-1914) - HONORS",
                    "courseNumber": "48BH",
                    "prefix": "ELIT",
                    "prefixParentId": 4816,
                    "prefixDescription": "English (Literature)",
                    "departmentParentId": 5069,
                    "department": "English (Literature)",
                    "begin": "F2018",
                    "end": "",
                    "minUnits": 4.0,
                    "maxUnits": 4.0,
                    "pathways": [],
                    "publishedCourseIdentifierYearTermId": null,
                    "position": 1,
                    "type": "Course"
                  }
                ],
                "attributes": [],
                "position": 1,
                "type": "CourseGroup"
              }
            ],
            "courseGroupConjunctions": [
              {
                "id": "8f566cd6-4edf-4490-cdff-08dd55dc249c",
                "sendingArticulationId": "7ecd7826-31ed-4984-6cf0-08dd55dc242e",
                "groupConjunction": "Or",
                "sendingCourseGroupBeginPosition": 0,
                "sendingCourseGroupEndPosition": 1
              }
            ],
            "type": "SendingArticulation",
            "attributes": []
          },
          "templateOverrides": [],
          "attributes": [],
          "receivingAttributes": []
        },
        "receivingAttributes": {
          "type": "Course",
          "courseAttributes": [],
          "attributes": []
        }
      },
      {
        "templateCellId": "982021f1-96e6-433e-adf4-08dd89a43052",
        "articulation": {
          "type": "Course",
          "course": {
            "courseIdentifierParentId": 243035,
            "courseTitle": "American Literature from Twain to the Moderns",
            "courseNumber": "222",
            "prefix": "ENGL",
            "prefixParentId": 2753,
            "prefixDescription": "English",
            "departmentParentId": 5170,
            "department": "English, Comparative Literature and Linguistics",
            "begin": "F2021",
            "end": "",
            "minUnits": 3.0,
            "maxUnits": 3.0,
            "pathways": []
          },
          "visibleCrossListedCourses": [],
          "courseAttributes": [],
          "sendingArticulation": {
            "noArticulationReason": null,
            "deniedCourses": [],
            "items": [
              {
                "courseConjunction": "And",
                "items": [
                  {
                    "visibleCrossListedCourses": [],
                    "requisites": [],
                    "attributes": [],
                    "courseIdentifierParentId": 353308,
                    "courseTitle": "Major American Writers (The Advent of Realism, 1865-1914)",
                    "courseNumber": "48B",
                    "prefix": "ELIT",
                    "prefixParentId": 4816,
                    "prefixDescription": "English (Literature)",
                    "departmentParentId": 5069,
                    "department": "English (Literature)",
                    "begin": "F2010",
                    "end": "",
                    "minUnits": 4.0,
                    "maxUnits": 4.0,
                    "pathways": [],
                    "publishedCourseIdentifierYearTermId": null,
                    "position": 0,
                    "type": "Course"
                  },
                  {
                    "visibleCrossListedCourses": [],
                    "requisites": [],
                    "attributes": [],
                    "courseIdentifierParentId": 254997,
                    "courseTitle": "Major American Writers (The Modern Age, 1914 - The Present)",
                    "courseNumber": "48C",
                    "prefix": "ELIT",
                    "prefixParentId": 4816,
                    "prefixDescription": "English (Literature)",
                    "departmentParentId": 5069,
                    "department": "English (Literature)",
                    "begin": "F1999",
                    "end": "",
                    "minUnits": 4.0,
                    "maxUnits": 4.0,
                    "pathways": [],
                    "publishedCourseIdentifierYearTermId": null,
                    "position": 1,
                    "type": "Course"
                  }
                ],
                "attributes": [],
                "position": 0,
                "type": "CourseGroup"
              },
              {
                "courseConjunction": "And",
                "items": [
                  {
                    "visibleCrossListedCourses": [],
                    "requisites": [],
                    "attributes": [],
                    "courseIdentifierParentId": 363729,
                    "courseTitle": "Major American Writers (The Advent of Realism, 1865-1914) - HONORS",
                    "courseNumber": "48BH",
                    "prefix": "ELIT",
                    "prefixParentId": 4816,
                    "prefixDescription": "English (Literature)",
                    "departmentParentId": 5069,
                    "department": "English (Literature)",
                    "begin": "F2018",
                    "end": "",
                    "minUnits": 4.0,
                    "maxUnits": 4.0,
                    "pathways": [],
                    "publishedCourseIdentifierYearTermId": null,
                    "position": 0,
                    "type": "Course"
                  },
                  {
                    "visibleCrossListedCourses": [],
                    "requisites": [],
                    "attributes": [],
                    "courseIdentifierParentId": 363730,
                    "courseTitle": "Major American Writers (The Modern Age, 1914-the Present) - HONORS",
                    "courseNumber": "48CH",
                    "prefix": "ELIT",
                    "prefixParentId": 4816,
                    "prefixDescription": "English (Literature)",
                    "departmentParentId": 5069,
                    "department": "English (Literature)",
                    "begin": "F2018",
                    "end": "",
                    "minUnits": 4.0,
                    "maxUnits": 4.0,
                    "pathways": [],
                    "publishedCourseIdentifierYearTermId": null,
                    "position": 1,
                    "type": "Course"
                  }
                ],
                "attributes": [],
                "position": 1,
                "type": "CourseGroup"
              }
            ],
            "courseGroupConjunctions": [
              {
                "id": "57915531-2e61-46dd-ce01-08dd55dc249c",
                "sendingArticulationId": "a11594e2-fad4-487d-6d13-08dd55dc242e",
                "groupConjunction": "Or",
                "sendingCourseGroupBeginPosition": 0,
                "sendingCourseGroupEndPosition": 1
              }
            ],
            "type": "SendingArticulation",
            "attributes": []
          },
          "templateOverrides": [],
          "attributes": [],
          "receivingAttributes": []
        },
        "receivingAttributes": {
          "type": "Course",
          "courseAttributes": [],
          "attributes": []
        }
      },
      {
        "templateCellId": "847c3ded-c3e6-4c85-adf5-08dd89a43052",
        "articulation": {
          "type": "Course",
          "course": {
            "courseIdentifierParentId": 145527,
            "courseTitle": "Children's Literature",
            "courseNumber": "341",
            "prefix": "ENGL",
            "prefixParentId": 2753,
            "prefixDescription": "English",
            "departmentParentId": 5170,
            "department": "English, Comparative Literature and Linguistics",
            "begin": "S2003",
            "end": "",
            "minUnits": 3.0,
            "maxUnits": 3.0,
            "pathways": []
          },
          "visibleCrossListedCourses": [],
          "courseAttributes": [],
          "sendingArticulation": {
            "noArticulationReason": "No Course Articulated",
            "deniedCourses": [],
            "items": [],
            "courseGroupConjunctions": [],
            "type": "SendingArticulation",
            "attributes": []
          },
          "templateOverrides": [],
          "attributes": [],
          "receivingAttributes": []
        },
        "receivingAttributes": {
          "type": "Course",
          "courseAttributes": [],
          "attributes": []
        }
      },
      {
        "templateCellId": "7b604c7f-eba0-401f-adf0-08dd89a43052",
        "articulation": {
          "type": "Course",
          "course": {
            "courseIdentifierParentId": 367072,
            "courseTitle": "Fundamental Concepts of Elementary Mathematics",
            "courseNumber": "303B",
            "prefix": "MATH",
            "prefixParentId": 10041,
            "prefixDescription": "Mathematics",
            "departmentParentId": 9055,
            "department": "Mathematics",
            "begin": "F2015",
            "end": "",
            "minUnits": 3.0,
            "maxUnits": 3.0,
            "pathways": []
          },
          "visibleCrossListedCourses": [],
          "courseAttributes": [],
          "sendingArticulation": {
            "noArticulationReason": "No Course Articulated",
            "deniedCourses": [],
            "items": [],
            "courseGroupConjunctions": [],
            "type": "SendingArticulation",
            "attributes": []
          },
          "templateOverrides": [],
          "attributes": [],
          "receivingAttributes": []
        },
        "receivingAttributes": {
          "type": "Course",
          "courseAttributes": [],
          "attributes": []
        }
      },
      {
        "templateCellId": "9c3e2288-d0ce-4560-2e11-08dd55dbff36",
        "articulation": {
          "type": "Course",
          "course": {
            "courseIdentifierParentId": 338397,
            "courseTitle": "American Government",
            "courseNumber": "100",
            "prefix": "POSC",
            "prefixParentId": 2042,
            "prefixDescription": "Political Science",
            "departmentParentId": 11050,
            "department": "Political Science",
            "begin": "F1995",
            "end": "",
            "minUnits": 3.0,
            "maxUnits": 3.0,
            "pathways": []
          },
          "visibleCrossListedCourses": [],
          "courseAttributes": [],
          "sendingArticulation": {
            "noArticulationReason": null,
            "deniedCourses": [],
            "items": [
              {
                "courseConjunction": "And",
                "items": [
                  {
                    "visibleCrossListedCourses": [],
                    "requisites": [],
                    "attributes": [],
                    "courseIdentifierParentId": 282754,
                    "courseTitle": "American Government and Politics",
                    "courseNumber": "C1000",
                    "prefix": "POLS",
                    "prefixParentId": 18724,
                    "prefixDescription": "Political Science",
                    "departmentParentId": 11018,
                    "department": "Political Science",
                    "begin": "F2025",
                    "end": "",
                    "minUnits": 5.0,
                    "maxUnits": 5.0,
                    "pathways": [],
                    "publishedCourseIdentifierYearTermId": null,
                    "position": 0,
                    "type": "Course"
                  }
                ],
                "attributes": [],
                "position": 0,
                "type": "CourseGroup"
              }
            ],
            "courseGroupConjunctions": [],
            "type": "SendingArticulation",
            "attributes": []
          },
          "templateOverrides": [],
          "attributes": [],
          "receivingAttributes": []
        },
        "receivingAttributes": {
          "type": "Course",
          "courseAttributes": [],
          "attributes": []
        }
      },
      {
        "templateCellId": "9a923107-f1ad-434f-2e14-08dd55dbff36",
        "articulation": {
          "type": "Course",
          "course": {
            "courseIdentifierParentId": 196717,
            "courseTitle": "Introduction to Liberal Studies",
            "courseNumber": "300",
            "prefix": "LBST",
            "prefixParentId": 5363,
            "prefixDescription": "Liberal Studies",
            "departmentParentId": 8456,
            "department": "Liberal Studies",
            "begin": "F2021",
            "end": "",
            "minUnits": 3.0,
            "maxUnits": 3.0,
            "pathways": []
          },
          "visibleCrossListedCourses": [],
          "courseAttributes": [],
          "sendingArticulation": {
            "noArticulationReason": "No Course Articulated",
            "deniedCourses": [],
            "items": [],
            "courseGroupConjunctions": [],
            "type": "SendingArticulation",
            "attributes": []
          },
          "templateOverrides": [],
          "attributes": [],
          "receivingAttributes": []
        },
        "receivingAttributes": {
          "type": "Course",
          "courseAttributes": [],
          "attributes": []
        }
      }
    ],
    "catalogYear": "{\"receivingCatalogYearBegin\":2025,\"receivingCatalogYearEnd\":2026,\"sendingCatalogYearBegin\":2025,\"sendingCatalogYearEnd\":2026}"
  },
  "validationFailure": null,
  "isSuccessful": true
}